{"liveId":420,"jsonVersion":2,"openTime":"11","closeTime":"22","notificationVersion":"1","notification":"","artList":[{"artId":0,"name":"-真天地開闢集団-ジグザグ"},{"artId":1,"name":"04 Limited Sazabys"},{"artId":2,"name":"BE:FIRST"},{"artId":3,"name":"BLUE ENCOUNT"},{"artId":4,"name":"DJ和"},{"artId":5,"name":"HANA"},{"artId":6,"name":"HEY-SMITH"},{"artId":7,"name":"Hump Back"},{"artId":8,"name":"KANA-BOON"},{"artId":9,"name":"ME:I"},{"artId":10,"name":"SAKANAMON"},{"artId":11,"name":"SEKAI NO OWARI"},{"artId":12,"name":"UVERworld"},{"artId":13,"name":"[Alexandros]"},{"artId":14,"name":"reGretGirl"},{"artId":15,"name":"ちゃんみな"},{"artId":16,"name":"アイナ・ジ・エンド"},{"artId":17,"name":"キュウソネコカミ"},{"artId":18,"name":"クリープハイプ"},{"artId":19,"name":"ポルカドットスティングレイ"},{"artId":20,"name":"マカロニえんぴつ"},{"artId":21,"name":"打首獄門同好会"},{"artId":22,"name":"結束バンド"},{"artId":23,"name":"阿部真央"}],"stageList":[{"stageId":0,"stageName":"LOTUS","stageNameShort":"LOTUS","colorName":"stage-grey"},{"stageId":1,"stageName":"GRASS","stageNameShort":"GRASS","colorName":"stage-blue"},{"stageId":2,"stageName":"HILLSIDE","stageNameShort":"HILLSIDE","colorName":"stage-green"},{"stageId":3,"stageName":"PARK","stageNameShort":"PARK","colorName":"stage-orange"}],"turnList":[{"turnId":0,"startTime":"12:30","min":40,"artId":2,"stageId":0},{"turnId":1,"startTime":"14:00","min":40,"artId":22,"stageId":0},{"turnId":2,"startTime":"15:30","min":40,"artId":13,"stageId":0},{"turnId":3,"startTime":"17:00","min":40,"artId":20,"stageId":0},{"turnId":4,"startTime":"18:45","min":55,"artId":11,"stageId":0},{"turnId":5,"startTime":"11:45","min":40,"artId":9,"stageId":1},{"turnId":6,"startTime":"13:15","min":40,"artId":15,"stageId":1},{"turnId":7,"startTime":"14:45","min":40,"artId":1,"stageId":1},{"turnId":8,"startTime":"16:15","min":40,"artId":18,"stageId":1},{"turnId":9,"startTime":"17:45","min":55,"artId":12,"stageId":1},{"turnId":10,"startTime":"19:45","min":30,"artId":4,"stageId":1},{"turnId":11,"startTime":"11:45","min":30,"artId":14,"stageId":2},{"turnId":12,"startTime":"13:05","min":30,"artId":19,"stageId":2},{"turnId":13,"startTime":"14:25","min":30,"artId":16,"stageId":2},{"turnId":14,"startTime":"15:45","min":30,"artId":8,"stageId":2},{"turnId":15,"startTime":"17:05","min":30,"artId":6,"stageId":2},{"turnId":16,"startTime":"18:25","min":30,"artId":23,"stageId":2},{"turnId":17,"startTime":"19:45","min":30,"artId":21,"stageId":2},{"turnId":18,"startTime":"12:25","min":30,"artId":10,"stageId":3},{"turnId":19,"startTime":"13:45","min":30,"artId":3,"stageId":3},{"turnId":20,"startTime":"15:05","min":30,"artId":5,"stageId":3},{"turnId":21,"startTime":"16:25","min":30,"artId":17,"stageId":3},{"turnId":22,"startTime":"17:45","min":30,"artId":7,"stageId":3},{"turnId":23,"startTime":"19:05","min":30,"artId":0,"stageId":3}]}