{"liveId":403,"jsonVersion":56,"openTime":"9","closeTime":"23","notificationVersion":"25","notification":"今年も特典会情報はユーザの皆さんから投稿いただいた情報を反映しています｡\n全てチェックできておりませんので公式情報も合わせてご確認ください｡\nご協力をお願いします！→ https://linktr.ee/stella_timetable \n\n・TGIFを追加しました\n・縁日タイテ(7/26版)を追加しました｡\n・Road to TIF結果を反映しました｡\n・特典会を一部追加(8/2更新)←👈️🆕\n・メインステージ争奪LIVE WINNER(AOAO)を反映←👈️🆕\n\n※コラボステージは､グループでの参加はタイテに反映していますがアイドル個人参加は省いています\n※終了時刻が未定の特典会は3時間として仮登録しています｡\n※長押し画面に､出演していないステージが表示されることがありますが､「大喜利ステージ」などのコラボステージも含んでいます｡","artList":[{"artId":0,"name":"#2i2"},{"artId":1,"name":"#ババババンビ"},{"artId":2,"name":"＝LOVE"},{"artId":3,"name":"≠ME"},{"artId":4,"name":"≒JOY"},{"artId":5,"name":"AOAO"},{"artId":6,"name":"Appare!"},{"artId":7,"name":"ASP"},{"artId":8,"name":"CANDY TUNE"},{"artId":9,"name":"CiON"},{"artId":10,"name":"CUTIE STREET"},{"artId":11,"name":"CYNHN"},{"artId":12,"name":"Devil ANTHEM."},{"artId":13,"name":"DIALOGUE＋"},{"artId":14,"name":"ExWHYZ"},{"artId":15,"name":"feelNEO"},{"artId":16,"name":"FES☆TIVE"},{"artId":17,"name":"fishbowl"},{"artId":18,"name":"GANG PARADE"},{"artId":19,"name":"Gran☆Ciel"},{"artId":20,"name":"Honey Devil"},{"artId":21,"name":"i-COL"},{"artId":22,"name":""},{"artId":23,"name":"IHOTEU"},{"artId":24,"name":"iLiFE!"},{"artId":25,"name":"INUWASI"},{"artId":26,"name":"iON!"},{"artId":27,"name":"Jams Collection"},{"artId":28,"name":"Juice=Juice"},{"artId":29,"name":"KAWAII LAB. MATES"},{"artId":30,"name":"KiSS KiSS"},{"artId":31,"name":"Kolokol"},{"artId":32,"name":"Lolly Talk"},{"artId":33,"name":"Luce Twinkle Wink☆"},{"artId":34,"name":"lyrical school"},{"artId":35,"name":"Ma'Scar'Piece"},{"artId":36,"name":"MEGAFON"},{"artId":37,"name":"Merry BAD TUNE."},{"artId":38,"name":"Mirror,Mirror"},{"artId":39,"name":"My_Stage"},{"artId":40,"name":"NANIMONO"},{"artId":41,"name":"NEO JAPONISM"},{"artId":42,"name":"NMB48"},{"artId":43,"name":"NMB48 チーム対抗出演権争奪戦 WINNERステージ"},{"artId":44,"name":"Onephony"},{"artId":45,"name":"Palette Parade"},{"artId":46,"name":"Peel the Apple"},{"artId":47,"name":"PIGGS"},{"artId":48,"name":"Pixel Ribbon　"},{"artId":49,"name":"PPE41"},{"artId":50,"name":"Primulav"},{"artId":51,"name":"Rain Tree"},{"artId":52,"name":"REIRIE"},{"artId":53,"name":"RiNCENT♯"},{"artId":54,"name":"Ringwanderung"},{"artId":55,"name":"アイドル革命"},{"artId":56,"name":"テラテラ"},{"artId":57,"name":"SAY-LA"},{"artId":58,"name":"selfish"},{"artId":59,"name":"StarWinK"},{"artId":60,"name":"STU48"},{"artId":61,"name":"SWEET STEADY"},{"artId":62,"name":"Task have Fun"},{"artId":63,"name":"THE ENCORE"},{"artId":64,"name":"THE ORCHESTRA TOKYO"},{"artId":65,"name":""},{"artId":66,"name":"TIF2025 × MOGRA コラボDJステージ"},{"artId":67,"name":"TIF2025ものまねFES"},{"artId":68,"name":"Tohkei"},{"artId":69,"name":"UtaGe!"},{"artId":70,"name":"WACK presents DREAMLIGHTS in TIF 〜もう聴けない！WACK名曲コレクション！〜"},{"artId":71,"name":"WHITE SCORPION"},{"artId":72,"name":""},{"artId":73,"name":"アキシブproject"},{"artId":74,"name":"アップアップガールズ（2）"},{"artId":75,"name":"アルテミスの翼"},{"artId":76,"name":"アンスリューム"},{"artId":77,"name":"かすみ草とステラ"},{"artId":78,"name":"カラフルスクリーム"},{"artId":79,"name":"グランドフィナーレ 15th Anniversary"},{"artId":80,"name":"こみっきゅおん！"},{"artId":81,"name":"さよならステイチューン"},{"artId":82,"name":"ジエメイ"},{"artId":83,"name":"シャルロット"},{"artId":84,"name":"シュレーディンガーの犬"},{"artId":85,"name":"シンデレラ宣言！"},{"artId":86,"name":"タイトル未定"},{"artId":87,"name":"つばきファクトリー"},{"artId":88,"name":"ドラマチックレコード"},{"artId":89,"name":"ナナコロビヤオキ"},{"artId":90,"name":"なみだ色の消しごむ"},{"artId":91,"name":"にしたんクリニックNダンス選手権"},{"artId":92,"name":"ネコプラpixx."},{"artId":93,"name":"のんふぃく！"},{"artId":94,"name":"ハルニシオン"},{"artId":95,"name":"フィロソフィーのダンス"},{"artId":96,"name":"フューチャーサイダー"},{"artId":97,"name":"まねきケチャ"},{"artId":98,"name":"ミームトーキョー"},{"artId":99,"name":"メインステージ争奪LIVE  WINNERステージ"},{"artId":100,"name":"め〜ぴよ"},{"artId":101,"name":""},{"artId":102,"name":"モノクローム"},{"artId":103,"name":""},{"artId":104,"name":"ラナキュラ"},{"artId":105,"name":"ラフ×ラフ"},{"artId":106,"name":"ロージークロニクル"},{"artId":107,"name":"雨のち、ハレーション"},{"artId":108,"name":"衛星とカラテア"},{"artId":109,"name":"高嶺のなでしこ"},{"artId":110,"name":"最終未来少女"},{"artId":111,"name":"諸橋沙夏（＝LOVE）"},{"artId":112,"name":"太陽と踊れ月夜に唄え"},{"artId":113,"name":"点染テンセイ少女。"},{"artId":114,"name":"東京女子流"},{"artId":115,"name":"豆柴の大群"},{"artId":116,"name":"透色ドロップ"},{"artId":117,"name":"二丁目の魁カミングアウト"},{"artId":118,"name":"虹のコンキスタドール"},{"artId":119,"name":"夜光性アミューズ"},{"artId":120,"name":"TIFで起きた朝は 〜今日ここ行きタイッテ！〜"},{"artId":121,"name":"黒川在庫処分センター2025 〜物販クロ歴史〜"},{"artId":122,"name":"TOKYO GRAVURE IDOL FESTIVAL 2025トークの部 DAY3"},{"artId":123,"name":"DICデジタル防災企画 DAY3"},{"artId":124,"name":"アイドル歌会 TIF出張版"},{"artId":125,"name":"ガラスガールpresents アイドルがみんなを救う！ 夏の人生相談２０２５"},{"artId":126,"name":"TIF2025×Zipper 表紙&amp;誌面掲載争奪戦！ お披露目ステージ"},{"artId":127,"name":"TIF2025×タテドラ トークステージ"},{"artId":128,"name":""},{"artId":129,"name":"TIF学園祭スペシャルトークステージ"},{"artId":130,"name":"TIF ASIA TOUR 2025 スペシャルトークステージ"},{"artId":131,"name":"ウラグランドフィナーレ"},{"artId":132,"name":"TGIF 1部"},{"artId":133,"name":"TGIF 2部"},{"artId":134,"name":"TGIF 3部"},{"artId":135,"name":"TGIF 4部"},{"artId":136,"name":"TGIF 5部"},{"artId":137,"name":"TGIF 6部"},{"artId":138,"name":"TGIF 7部"},{"artId":139,"name":"As a Cutie Pomeranian"},{"artId":140,"name":"BABYTANTS"},{"artId":141,"name":"BOY MEETS HARU"},{"artId":142,"name":"FLAPSTAR"},{"artId":143,"name":"FandL"},{"artId":144,"name":"MARBLE TALE"},{"artId":145,"name":"OS1"},{"artId":146,"name":"PATI PATI CANDY...☆"},{"artId":147,"name":"PUREMORPH"},{"artId":148,"name":""},{"artId":149,"name":"UNION FLEUR"},{"artId":150,"name":"おーらびっと"},{"artId":151,"name":"もあに～と"},{"artId":152,"name":"キュータルチェ"},{"artId":153,"name":"メルクマールメルマール"},{"artId":154,"name":"強くてニューゲーム。"},{"artId":155,"name":"思い出とプレゼント"},{"artId":156,"name":"星屑ラビリンス"},{"artId":157,"name":"最愛のマルベリー"},{"artId":158,"name":"気まぐれモンスター"},{"artId":159,"name":"蛍"},{"artId":160,"name":"TIF de Debut（Pastel Closet）"},{"artId":161,"name":"LumiUnion"},{"artId":162,"name":"ポラライト"},{"artId":163,"name":"Root mimi (才川・天宮・黒嵜）"},{"artId":164,"name":"花渕友香・うりぼ・姫乃みゆう・君塚爽来"},{"artId":165,"name":"千歳ゆず・小嶋明梨・カワシマユカ"},{"artId":166,"name":"櫻葉あんな・夢実こと・七草いのり・胡蝶みお"},{"artId":167,"name":"水木春花・水緒みみ・真夜中おとぎ"},{"artId":168,"name":"橘亜沙美・飯島茉由・桜井もな・桜井優美・碧海りな・朝長ゆきの"},{"artId":169,"name":"みうぱ"},{"artId":170,"name":"百野綾華・白羽根優衣・佐野るか"},{"artId":171,"name":"Ange☆Reve"},{"artId":172,"name":"城崎桃華"}],"stageList":[{"stageId":0,"stageName":"HOT STAGE","stageNameShort":"HOT STAGE","colorName":"stage-red"},{"stageId":1,"stageName":"HEAT GARAGE","stageNameShort":"HEAT GARAGE","colorName":"stage-deepOrange"},{"stageId":2,"stageName":"SMILE GARDEN","stageNameShort":"SMILE GARDEN","colorName":"stage-light-green"},{"stageId":3,"stageName":"DOLL FACTORY","stageNameShort":"DOLL FACTORY","colorName":"stage-green"},{"stageId":4,"stageName":"SKY STAGE","stageNameShort":"SKY STAGE","colorName":"stage-lightBlue"},{"stageId":5,"stageName":"TOROCCO PARK","stageNameShort":"TOROCCO PARK","colorName":"stage-indigo"},{"stageId":6,"stageName":"浮島 STAGE","stageNameShort":"浮島 STAGE","colorName":"stage-orange"},{"stageId":7,"stageName":"INFO CENTRE","stageNameShort":"INFO CENTRE","colorName":"stage-purple"},{"stageId":8,"stageName":"TGIF (TOKYO GRAVURE IDOL FESTIVAL)","stageNameShort":"TGIF (TOKYO GRAVURE IDOL FESTIVAL)","colorName":"stage-redGrey"},{"stageId":9,"stageName":"縁日A","stageNameShort":"縁日A","colorName":"stage-greenGrey"},{"stageId":10,"stageName":"縁日B","stageNameShort":"縁日B","colorName":"stage-greenGrey"},{"stageId":11,"stageName":"縁日C","stageNameShort":"縁日C","colorName":"stage-greenGrey"},{"stageId":12,"stageName":"縁日D","stageNameShort":"縁日D","colorName":"stage-greenGrey"},{"stageId":13,"stageName":"縁日E","stageNameShort":"縁日E","colorName":"stage-greenGrey"},{"stageId":14,"stageName":"縁日F","stageNameShort":"縁日F","colorName":"stage-greenGrey"},{"stageId":15,"stageName":"縁日G","stageNameShort":"縁日G","colorName":"stage-greenGrey"},{"stageId":16,"stageName":"縁日H","stageNameShort":"縁日H","colorName":"stage-greenGrey"},{"stageId":17,"stageName":"A-1 Kolokol","stageNameShort":"A-1","colorName":"stage-grey"},{"stageId":18,"stageName":"A-2 THE ORCHESTRA TOKYO","stageNameShort":"A-2","colorName":"stage-grey"},{"stageId":19,"stageName":"A-3 Ringwanderung","stageNameShort":"A-3","colorName":"stage-grey"},{"stageId":20,"stageName":"A-4 Mirror,Mirror","stageNameShort":"A-4","colorName":"stage-grey"},{"stageId":21,"stageName":"A-5 Merry BAD TUNE.","stageNameShort":"A-5","colorName":"stage-grey"},{"stageId":22,"stageName":"A-6 タイトル未定","stageNameShort":"A-6","colorName":"stage-grey"},{"stageId":23,"stageName":"A-7 selfish","stageNameShort":"A-7","colorName":"stage-grey"},{"stageId":24,"stageName":"A-8 fishbowl","stageNameShort":"A-8","colorName":"stage-grey"},{"stageId":25,"stageName":"A-9 CYNHN","stageNameShort":"A-9","colorName":"stage-grey"},{"stageId":26,"stageName":"A-10 ミームトーキョー","stageNameShort":"A-10","colorName":"stage-grey"},{"stageId":27,"stageName":"A-11 さよならステイチューン","stageNameShort":"A-11","colorName":"stage-grey"},{"stageId":28,"stageName":"A-12 虹のコンキスタドール","stageNameShort":"A-12","colorName":"stage-grey"},{"stageId":29,"stageName":"A-13 #2i2","stageNameShort":"A-13","colorName":"stage-grey"},{"stageId":30,"stageName":"A-14 #ババババンビ","stageNameShort":"A-14","colorName":"stage-grey"},{"stageId":31,"stageName":"A-15 ","stageNameShort":"A-15","colorName":"stage-grey"},{"stageId":32,"stageName":"B-1 AOAO","stageNameShort":"B-1","colorName":"stage-grey"},{"stageId":33,"stageName":"B-2 ","stageNameShort":"B-2","colorName":"stage-grey"},{"stageId":34,"stageName":"B-3 NEO JAPONISM","stageNameShort":"B-3","colorName":"stage-grey"},{"stageId":35,"stageName":"B-4 Onephony","stageNameShort":"B-4","colorName":"stage-grey"},{"stageId":36,"stageName":"B-5 Appare!","stageNameShort":"B-5","colorName":"stage-grey"},{"stageId":37,"stageName":"B-6 Palette Parade","stageNameShort":"B-6","colorName":"stage-grey"},{"stageId":38,"stageName":"B-7 UtaGe!","stageNameShort":"B-7","colorName":"stage-grey"},{"stageId":39,"stageName":"B-8 CiON","stageNameShort":"B-8","colorName":"stage-grey"},{"stageId":40,"stageName":"C-1 KAWAII LAB. MATES","stageNameShort":"C-1","colorName":"stage-grey"},{"stageId":41,"stageName":"C-2 CUTIE STREET","stageNameShort":"C-2","colorName":"stage-grey"},{"stageId":42,"stageName":"C-3 SWEET STEADY","stageNameShort":"C-3","colorName":"stage-grey"},{"stageId":43,"stageName":"C-4 CANDY TUNE","stageNameShort":"C-4","colorName":"stage-grey"},{"stageId":44,"stageName":"C-5 FES☆TIVE","stageNameShort":"C-5","colorName":"stage-grey"},{"stageId":45,"stageName":"C-6 Jams Collection","stageNameShort":"C-6","colorName":"stage-grey"},{"stageId":46,"stageName":"C-7 雨のち、ハレーション","stageNameShort":"C-7","colorName":"stage-grey"},{"stageId":47,"stageName":"C-8 Pastel Closet","stageNameShort":"C-8","colorName":"stage-grey"},{"stageId":48,"stageName":"D-1 こみっきゅおん！","stageNameShort":"D-1","colorName":"stage-grey"},{"stageId":49,"stageName":"D-2 Devil ANTHEM.","stageNameShort":"D-2","colorName":"stage-grey"},{"stageId":50,"stageName":"D-3 INUWASI","stageNameShort":"D-3","colorName":"stage-grey"},{"stageId":51,"stageName":"D-4 ","stageNameShort":"D-4","colorName":"stage-grey"},{"stageId":52,"stageName":"D-5 DIALOGUE＋","stageNameShort":"D-5","colorName":"stage-grey"},{"stageId":53,"stageName":"D-6 feelNEO","stageNameShort":"D-6","colorName":"stage-grey"},{"stageId":54,"stageName":"E-1 城崎桃華・初季","stageNameShort":"E-1","colorName":"stage-grey"},{"stageId":55,"stageName":"E-2 Gran☆Ciel","stageNameShort":"E-2","colorName":"stage-grey"},{"stageId":56,"stageName":"E-3 Luce Twinkle Wink☆","stageNameShort":"E-3","colorName":"stage-grey"},{"stageId":57,"stageName":"E-4 太陽と踊れ月夜に唄え","stageNameShort":"E-4","colorName":"stage-grey"},{"stageId":58,"stageName":"E-5 Honey Devil","stageNameShort":"E-5","colorName":"stage-grey"},{"stageId":59,"stageName":"E-6 IHOTEU","stageNameShort":"E-6","colorName":"stage-grey"},{"stageId":60,"stageName":"E-7 lyrical school","stageNameShort":"E-7","colorName":"stage-grey"},{"stageId":61,"stageName":"E-8 Ma'Scar'Piece","stageNameShort":"E-8","colorName":"stage-grey"},{"stageId":62,"stageName":"E-9 My_Stage","stageNameShort":"E-9","colorName":"stage-grey"},{"stageId":63,"stageName":"E-10 NANIMONO","stageNameShort":"E-10","colorName":"stage-grey"},{"stageId":64,"stageName":"F-1 ","stageNameShort":"F-1","colorName":"stage-grey"},{"stageId":65,"stageName":"F-2 Peel the Apple","stageNameShort":"F-2","colorName":"stage-grey"},{"stageId":66,"stageName":"F-3 テラテラ","stageNameShort":"F-3","colorName":"stage-grey"},{"stageId":67,"stageName":"F-4 PIGGS","stageNameShort":"F-4","colorName":"stage-grey"},{"stageId":68,"stageName":"F-5 PPE41","stageNameShort":"F-5","colorName":"stage-grey"},{"stageId":69,"stageName":"F-6 Primulav","stageNameShort":"F-6","colorName":"stage-grey"},{"stageId":70,"stageName":"F-7 RiNCENT♯","stageNameShort":"F-7","colorName":"stage-grey"},{"stageId":71,"stageName":"F-8 SAY-LA","stageNameShort":"F-8","colorName":"stage-grey"},{"stageId":72,"stageName":"G-1 Rain Tree","stageNameShort":"G-1","colorName":"stage-grey"},{"stageId":73,"stageName":"G-2 WHITE SCORPION","stageNameShort":"G-2","colorName":"stage-grey"},{"stageId":74,"stageName":"G-3 ラフ×ラフ","stageNameShort":"G-3","colorName":"stage-grey"},{"stageId":75,"stageName":"G-4 StarWink","stageNameShort":"G-4","colorName":"stage-grey"},{"stageId":76,"stageName":"G-5 Task have Fun","stageNameShort":"G-5","colorName":"stage-grey"},{"stageId":77,"stageName":"G-6 THE ENCORE","stageNameShort":"G-6","colorName":"stage-grey"},{"stageId":78,"stageName":"G-7 なみだ色の消しごむ","stageNameShort":"G-7","colorName":"stage-grey"},{"stageId":79,"stageName":"G-8 アイドル革命","stageNameShort":"G-8","colorName":"stage-grey"},{"stageId":80,"stageName":"G-9 アップアップガールズ（2）","stageNameShort":"G-9","colorName":"stage-grey"},{"stageId":81,"stageName":"G-10 アキシブproject","stageNameShort":"G-10","colorName":"stage-grey"},{"stageId":82,"stageName":"H-1 アルテミスの翼","stageNameShort":"H-1","colorName":"stage-grey"},{"stageId":83,"stageName":"H-2 アンスリューム","stageNameShort":"H-2","colorName":"stage-grey"},{"stageId":84,"stageName":"H-3 ラナキュラ","stageNameShort":"H-3","colorName":"stage-grey"},{"stageId":85,"stageName":"H-4 カラフルスクリーム","stageNameShort":"H-4","colorName":"stage-grey"},{"stageId":86,"stageName":"H-5 かすみ草とステラ","stageNameShort":"H-5","colorName":"stage-grey"},{"stageId":87,"stageName":"H-6 ","stageNameShort":"H-6","colorName":"stage-grey"},{"stageId":88,"stageName":"H-7 ジエメイ","stageNameShort":"H-7","colorName":"stage-grey"},{"stageId":89,"stageName":"H-8 シャルロット","stageNameShort":"H-8","colorName":"stage-grey"},{"stageId":90,"stageName":"I-1 シュレーディンガーの犬","stageNameShort":"I-1","colorName":"stage-grey"},{"stageId":91,"stageName":"I-2 シンデレラ宣言！","stageNameShort":"I-2","colorName":"stage-grey"},{"stageId":92,"stageName":"I-3 ドラマチックレコード","stageNameShort":"I-3","colorName":"stage-grey"},{"stageId":93,"stageName":"I-4 ネコプラpixx.","stageNameShort":"I-4","colorName":"stage-grey"},{"stageId":94,"stageName":"I-5 ハルニシオン","stageNameShort":"I-5","colorName":"stage-grey"},{"stageId":95,"stageName":"I-6 ","stageNameShort":"I-6","colorName":"stage-grey"},{"stageId":96,"stageName":"I-7 フィロソフィーのダンス","stageNameShort":"I-7","colorName":"stage-grey"},{"stageId":97,"stageName":"I-8 フューチャーサイダー","stageNameShort":"I-8","colorName":"stage-grey"},{"stageId":98,"stageName":"I-9 まねきケチャ","stageNameShort":"I-9","colorName":"stage-grey"},{"stageId":99,"stageName":"I-10 モノクローム","stageNameShort":"I-10","colorName":"stage-grey"},{"stageId":100,"stageName":"J-1 め〜ぴよ","stageNameShort":"J-1","colorName":"stage-grey"},{"stageId":101,"stageName":"J-2 衛星とカラテア","stageNameShort":"J-2","colorName":"stage-grey"},{"stageId":102,"stageName":"J-3 高嶺のなでしこ","stageNameShort":"J-3","colorName":"stage-grey"},{"stageId":103,"stageName":"J-4 最終未来少女","stageNameShort":"J-4","colorName":"stage-grey"},{"stageId":104,"stageName":"J-5 ASP","stageNameShort":"J-5","colorName":"stage-grey"},{"stageId":105,"stageName":"J-6 ExWHYZ","stageNameShort":"J-6","colorName":"stage-grey"},{"stageId":106,"stageName":"J-7 GANG PARADE","stageNameShort":"J-7","colorName":"stage-grey"},{"stageId":107,"stageName":"J-8 KiSS KiSS","stageNameShort":"J-8","colorName":"stage-grey"},{"stageId":108,"stageName":"J-9 豆柴の大群","stageNameShort":"J-9","colorName":"stage-grey"},{"stageId":109,"stageName":"J-10 WACK","stageNameShort":"J-10","colorName":"stage-grey"},{"stageId":110,"stageName":"K-1 i-COL","stageNameShort":"K-1","colorName":"stage-grey"},{"stageId":111,"stageName":"K-2 iLiFE!","stageNameShort":"K-2","colorName":"stage-grey"},{"stageId":112,"stageName":"K-3 iON!","stageNameShort":"K-3","colorName":"stage-grey"},{"stageId":113,"stageName":"K-4 MEGAFON","stageNameShort":"K-4","colorName":"stage-grey"},{"stageId":114,"stageName":"K-5 ナナコロビヤオキ","stageNameShort":"K-5","colorName":"stage-grey"},{"stageId":115,"stageName":"K-6 のんふぃく！","stageNameShort":"K-6","colorName":"stage-grey"},{"stageId":116,"stageName":"K-7 夜光性アミューズ","stageNameShort":"K-7","colorName":"stage-grey"},{"stageId":117,"stageName":"K-8 点染テンセイ少女。","stageNameShort":"K-8","colorName":"stage-grey"},{"stageId":118,"stageName":"K-9 東京おとめ太鼓","stageNameShort":"K-9","colorName":"stage-grey"},{"stageId":119,"stageName":"K-10 透色ドロップ","stageNameShort":"K-10","colorName":"stage-grey"},{"stageId":120,"stageName":"K-11 二丁目の魁カミングアウト","stageNameShort":"K-11","colorName":"stage-grey"},{"stageId":121,"stageName":"K-12 Tohkei","stageNameShort":"K-12","colorName":"stage-grey"},{"stageId":122,"stageName":"特典会 場所不明","stageNameShort":"特典会 場所不明","colorName":"stage-grey"}],"turnList":[{"turnId":0,"startTime":"10:00","min":30,"artId":106,"stageId":0},{"turnId":1,"startTime":"10:40","min":30,"artId":13,"stageId":0},{"turnId":2,"startTime":"11:20","min":30,"artId":52,"stageId":0},{"turnId":3,"startTime":"12:00","min":30,"artId":14,"stageId":0},{"turnId":4,"startTime":"12:40","min":30,"artId":42,"stageId":0},{"turnId":5,"startTime":"13:20","min":20,"artId":5,"stageId":0},{"turnId":6,"startTime":"13:50","min":30,"artId":8,"stageId":0},{"turnId":7,"startTime":"14:30","min":30,"artId":60,"stageId":0},{"turnId":8,"startTime":"15:10","min":30,"artId":10,"stageId":0},{"turnId":9,"startTime":"15:50","min":30,"artId":87,"stageId":0},{"turnId":10,"startTime":"16:30","min":30,"artId":28,"stageId":0},{"turnId":11,"startTime":"17:10","min":30,"artId":24,"stageId":0},{"turnId":12,"startTime":"17:50","min":30,"artId":4,"stageId":0},{"turnId":13,"startTime":"18:30","min":30,"artId":3,"stageId":0},{"turnId":14,"startTime":"19:10","min":35,"artId":2,"stageId":0},{"turnId":15,"startTime":"19:55","min":50,"artId":79,"stageId":0,"collabArtList":[2,3,4,6,27,86,109,62,114,90,118,41,16,46,161],"title":"グランドフィナーレ 15th Anniversary"},{"turnId":16,"startTime":"10:00","min":30,"artId":6,"stageId":1,"collabArtList":[6,69,45],"title":"Tシャツ着用者限定ステージ PLAYYTE DAY "},{"turnId":17,"startTime":"10:45","min":25,"artId":21,"stageId":1},{"turnId":18,"startTime":"11:10","min":25,"artId":105,"stageId":1},{"turnId":19,"startTime":"11:35","min":25,"artId":16,"stageId":1},{"turnId":20,"startTime":"12:10","min":25,"artId":85,"stageId":1},{"turnId":21,"startTime":"12:35","min":25,"artId":119,"stageId":1},{"turnId":22,"startTime":"13:00","min":25,"artId":87,"stageId":1},{"turnId":23,"startTime":"13:25","min":25,"artId":32,"stageId":1},{"turnId":24,"startTime":"14:00","min":45,"artId":70,"stageId":1},{"turnId":25,"startTime":"14:55","min":15,"artId":55,"stageId":1},{"turnId":26,"startTime":"15:10","min":60,"artId":23,"stageId":1,"collabArtList":[118,33,23,59,50,102,32],"title":"TIF ASIA TOUR 2025 スペシャルライブステージ"},{"turnId":27,"startTime":"16:25","min":25,"artId":44,"stageId":1},{"turnId":28,"startTime":"16:50","min":25,"artId":0,"stageId":1},{"turnId":29,"startTime":"17:15","min":25,"artId":18,"stageId":1},{"turnId":30,"startTime":"17:40","min":25,"artId":47,"stageId":1},{"turnId":31,"startTime":"18:15","min":25,"artId":90,"stageId":1},{"turnId":32,"startTime":"18:40","min":25,"artId":64,"stageId":1},{"turnId":33,"startTime":"19:05","min":25,"artId":61,"stageId":1},{"turnId":34,"startTime":"19:45","min":25,"artId":77,"stageId":1},{"turnId":35,"startTime":"20:10","min":25,"artId":28,"stageId":1},{"turnId":36,"startTime":"20:35","min":25,"artId":88,"stageId":1},{"turnId":37,"startTime":"09:25","min":15,"artId":103,"stageId":2,"collabArtList":[29,46,35],"title":"ラジオ体操"},{"turnId":38,"startTime":"09:40","min":20,"artId":111,"stageId":2},{"turnId":39,"startTime":"10:00","min":20,"artId":29,"stageId":2},{"turnId":40,"startTime":"10:20","min":20,"artId":46,"stageId":2},{"turnId":41,"startTime":"10:40","min":20,"artId":35,"stageId":2},{"turnId":42,"startTime":"11:10","min":20,"artId":5,"stageId":2},{"turnId":43,"startTime":"11:30","min":20,"artId":69,"stageId":2},{"turnId":44,"startTime":"11:50","min":25,"artId":101,"stageId":2,"collabArtList":[106,53],"title":"モーニング娘。 大好きステージ"},{"turnId":45,"startTime":"12:25","min":20,"artId":34,"stageId":2},{"turnId":46,"startTime":"12:45","min":20,"artId":7,"stageId":2},{"turnId":47,"startTime":"13:05","min":25,"artId":21,"stageId":2,"collabArtList":[21,37],"title":"スペシャルコラボステージ"},{"turnId":48,"startTime":"13:40","min":20,"artId":117,"stageId":2},{"turnId":49,"startTime":"14:00","min":20,"artId":93,"stageId":2},{"turnId":50,"startTime":"14:20","min":20,"artId":13,"stageId":2},{"turnId":51,"startTime":"14:50","min":20,"artId":91,"stageId":2},{"turnId":52,"startTime":"15:10","min":20,"artId":58,"stageId":2},{"turnId":53,"startTime":"15:30","min":20,"artId":96,"stageId":2},{"turnId":54,"startTime":"16:00","min":20,"artId":113,"stageId":2},{"turnId":55,"startTime":"16:20","min":20,"artId":78,"stageId":2},{"turnId":56,"startTime":"16:40","min":20,"artId":43,"stageId":2},{"turnId":57,"startTime":"17:10","min":20,"artId":39,"stageId":2},{"turnId":58,"startTime":"17:30","min":20,"artId":6,"stageId":2},{"turnId":59,"startTime":"17:50","min":25,"artId":74,"stageId":2,"collabArtList":[74,1,108,77],"title":"15周年特別企画 IDOL SUMMER JAMBOREE  〜抽選コラボ DAY3〜"},{"turnId":60,"startTime":"18:25","min":20,"artId":63,"stageId":2},{"turnId":61,"startTime":"18:45","min":20,"artId":76,"stageId":2},{"turnId":62,"startTime":"19:05","min":20,"artId":109,"stageId":2},{"turnId":63,"startTime":"19:35","min":20,"artId":9,"stageId":2},{"turnId":64,"startTime":"19:55","min":20,"artId":37,"stageId":2},{"turnId":65,"startTime":"20:15","min":20,"artId":54,"stageId":2},{"turnId":66,"startTime":"20:35","min":20,"artId":25,"stageId":2},{"turnId":67,"startTime":"10:00","min":20,"artId":19,"stageId":3},{"turnId":68,"startTime":"10:20","min":20,"artId":20,"stageId":3},{"turnId":69,"startTime":"10:40","min":20,"artId":53,"stageId":3},{"turnId":70,"startTime":"11:05","min":15,"artId":56,"stageId":3},{"turnId":71,"startTime":"11:20","min":15,"artId":65,"stageId":3,"collabArtList":[160],"title":"TIF de Debut"},{"turnId":72,"startTime":"11:35","min":20,"artId":36,"stageId":3},{"turnId":73,"startTime":"11:55","min":20,"artId":23,"stageId":3},{"turnId":74,"startTime":"12:20","min":20,"artId":50,"stageId":3},{"turnId":75,"startTime":"12:40","min":20,"artId":48,"stageId":3},{"turnId":76,"startTime":"13:00","min":20,"artId":45,"stageId":3},{"turnId":77,"startTime":"13:25","min":20,"artId":68,"stageId":3},{"turnId":78,"startTime":"13:45","min":20,"artId":82,"stageId":3},{"turnId":79,"startTime":"14:05","min":20,"artId":1,"stageId":3},{"turnId":80,"startTime":"14:30","min":20,"artId":107,"stageId":3},{"turnId":81,"startTime":"14:50","min":20,"artId":73,"stageId":3},{"turnId":82,"startTime":"15:10","min":20,"artId":110,"stageId":3},{"turnId":83,"startTime":"15:35","min":20,"artId":26,"stageId":3},{"turnId":84,"startTime":"15:55","min":20,"artId":83,"stageId":3},{"turnId":85,"startTime":"16:15","min":20,"artId":108,"stageId":3},{"turnId":86,"startTime":"16:40","min":60,"artId":67,"stageId":3},{"turnId":87,"startTime":"17:45","min":20,"artId":115,"stageId":3},{"turnId":88,"startTime":"18:05","min":20,"artId":12,"stageId":3},{"turnId":89,"startTime":"18:25","min":20,"artId":27,"stageId":3},{"turnId":90,"startTime":"18:50","min":20,"artId":95,"stageId":3},{"turnId":91,"startTime":"19:10","min":20,"artId":114,"stageId":3},{"turnId":92,"startTime":"19:55","min":60,"artId":66,"stageId":3},{"turnId":93,"startTime":"10:15","min":15,"artId":96,"stageId":4},{"turnId":94,"startTime":"10:30","min":15,"artId":23,"stageId":4},{"turnId":95,"startTime":"10:45","min":15,"artId":50,"stageId":4},{"turnId":96,"startTime":"11:00","min":20,"artId":30,"stageId":4},{"turnId":97,"startTime":"11:25","min":15,"artId":102,"stageId":4},{"turnId":98,"startTime":"11:40","min":15,"artId":39,"stageId":4},{"turnId":99,"startTime":"11:55","min":15,"artId":116,"stageId":4},{"turnId":100,"startTime":"12:10","min":15,"artId":29,"stageId":4},{"turnId":101,"startTime":"12:30","min":15,"artId":98,"stageId":4},{"turnId":102,"startTime":"12:45","min":15,"artId":113,"stageId":4},{"turnId":103,"startTime":"13:00","min":15,"artId":104,"stageId":4},{"turnId":104,"startTime":"13:15","min":15,"artId":61,"stageId":4},{"turnId":105,"startTime":"14:15","min":15,"artId":75,"stageId":4},{"turnId":106,"startTime":"14:30","min":15,"artId":84,"stageId":4},{"turnId":107,"startTime":"14:45","min":15,"artId":63,"stageId":4},{"turnId":108,"startTime":"15:00","min":15,"artId":106,"stageId":4},{"turnId":109,"startTime":"15:20","min":15,"artId":5,"stageId":4},{"turnId":110,"startTime":"15:35","min":15,"artId":53,"stageId":4},{"turnId":111,"startTime":"15:50","min":15,"artId":35,"stageId":4},{"turnId":112,"startTime":"16:05","min":15,"artId":89,"stageId":4},{"turnId":113,"startTime":"16:25","min":15,"artId":94,"stageId":4},{"turnId":114,"startTime":"16:40","min":15,"artId":15,"stageId":4},{"turnId":115,"startTime":"16:55","min":15,"artId":12,"stageId":4},{"turnId":116,"startTime":"17:10","min":15,"artId":109,"stageId":4},{"turnId":117,"startTime":"17:30","min":15,"artId":58,"stageId":4},{"turnId":118,"startTime":"17:45","min":15,"artId":49,"stageId":4},{"turnId":119,"startTime":"18:00","min":15,"artId":114,"stageId":4},{"turnId":120,"startTime":"18:15","min":15,"artId":62,"stageId":4},{"turnId":121,"startTime":"18:35","min":15,"artId":112,"stageId":4},{"turnId":122,"startTime":"18:50","min":15,"artId":34,"stageId":4},{"turnId":123,"startTime":"19:05","min":15,"artId":69,"stageId":4},{"turnId":124,"startTime":"19:20","min":15,"artId":41,"stageId":4},{"turnId":125,"startTime":"19:40","min":15,"artId":38,"stageId":4},{"turnId":126,"startTime":"19:55","min":15,"artId":31,"stageId":4},{"turnId":127,"startTime":"20:10","min":15,"artId":11,"stageId":4},{"turnId":128,"startTime":"20:25","min":15,"artId":17,"stageId":4},{"turnId":129,"startTime":"10:00","min":20,"artId":74,"stageId":5},{"turnId":130,"startTime":"10:20","min":20,"artId":80,"stageId":5},{"turnId":131,"startTime":"10:40","min":20,"artId":97,"stageId":5},{"turnId":132,"startTime":"11:05","min":20,"artId":59,"stageId":5},{"turnId":133,"startTime":"11:25","min":20,"artId":81,"stageId":5},{"turnId":134,"startTime":"11:45","min":20,"artId":33,"stageId":5},{"turnId":135,"startTime":"12:10","min":20,"artId":75,"stageId":5},{"turnId":136,"startTime":"12:30","min":20,"artId":15,"stageId":5},{"turnId":137,"startTime":"12:50","min":20,"artId":112,"stageId":5},{"turnId":138,"startTime":"13:15","min":20,"artId":38,"stageId":5},{"turnId":139,"startTime":"13:35","min":20,"artId":94,"stageId":5},{"turnId":140,"startTime":"13:55","min":20,"artId":108,"stageId":5},{"turnId":141,"startTime":"14:25","min":20,"artId":51,"stageId":5},{"turnId":142,"startTime":"14:45","min":20,"artId":71,"stageId":5},{"turnId":143,"startTime":"15:05","min":30,"artId":105,"stageId":5,"collabArtList":[77,1,115,105],"title":"アイドル天下一大喜利武道会 〜TIF ROUND〜"},{"turnId":144,"startTime":"15:40","min":20,"artId":92,"stageId":5},{"turnId":145,"startTime":"16:00","min":20,"artId":40,"stageId":5},{"turnId":146,"startTime":"16:20","min":20,"artId":27,"stageId":5},{"turnId":147,"startTime":"16:45","min":20,"artId":84,"stageId":5},{"turnId":148,"startTime":"17:05","min":20,"artId":57,"stageId":5},{"turnId":149,"startTime":"17:25","min":20,"artId":31,"stageId":5},{"turnId":150,"startTime":"17:50","min":20,"artId":11,"stageId":5},{"turnId":151,"startTime":"18:10","min":20,"artId":118,"stageId":5},{"turnId":152,"startTime":"18:30","min":20,"artId":86,"stageId":5},{"turnId":153,"startTime":"10:00","min":15,"artId":73,"stageId":6},{"turnId":154,"startTime":"10:15","min":15,"artId":98,"stageId":6},{"turnId":155,"startTime":"10:30","min":15,"artId":48,"stageId":6},{"turnId":156,"startTime":"10:45","min":15,"artId":110,"stageId":6},{"turnId":157,"startTime":"11:05","min":15,"artId":57,"stageId":6},{"turnId":158,"startTime":"11:20","min":15,"artId":83,"stageId":6},{"turnId":159,"startTime":"11:35","min":15,"artId":49,"stageId":6},{"turnId":160,"startTime":"11:50","min":15,"artId":46,"stageId":6},{"turnId":161,"startTime":"12:10","min":15,"artId":92,"stageId":6},{"turnId":162,"startTime":"12:25","min":15,"artId":97,"stageId":6},{"turnId":163,"startTime":"12:40","min":15,"artId":102,"stageId":6},{"turnId":164,"startTime":"12:55","min":15,"artId":40,"stageId":6},{"turnId":165,"startTime":"13:15","min":15,"artId":100,"stageId":6},{"turnId":166,"startTime":"13:30","min":15,"artId":59,"stageId":6},{"turnId":167,"startTime":"13:45","min":15,"artId":89,"stageId":6},{"turnId":168,"startTime":"14:00","min":15,"artId":41,"stageId":6},{"turnId":169,"startTime":"14:25","min":15,"artId":26,"stageId":6},{"turnId":170,"startTime":"14:40","min":15,"artId":44,"stageId":6},{"turnId":171,"startTime":"14:55","min":15,"artId":54,"stageId":6},{"turnId":172,"startTime":"15:10","min":15,"artId":95,"stageId":6},{"turnId":173,"startTime":"15:30","min":15,"artId":80,"stageId":6},{"turnId":174,"startTime":"15:45","min":15,"artId":81,"stageId":6},{"turnId":175,"startTime":"16:00","min":15,"artId":1,"stageId":6},{"turnId":176,"startTime":"16:20","min":15,"artId":93,"stageId":6},{"turnId":177,"startTime":"16:35","min":15,"artId":90,"stageId":6},{"turnId":178,"startTime":"16:50","min":15,"artId":116,"stageId":6},{"turnId":179,"startTime":"17:05","min":15,"artId":86,"stageId":6},{"turnId":180,"startTime":"17:25","min":15,"artId":19,"stageId":6},{"turnId":181,"startTime":"17:40","min":15,"artId":78,"stageId":6},{"turnId":182,"startTime":"17:55","min":15,"artId":104,"stageId":6},{"turnId":183,"startTime":"18:25","min":25,"artId":22,"stageId":6,"collabArtList":[6,117,16],"title":"IDOL盆踊りナイト DAY3"},{"turnId":184,"startTime":"10:00","min":45,"artId":120,"stageId":7},{"turnId":185,"startTime":"10:55","min":60,"artId":121,"stageId":7},{"turnId":186,"startTime":"12:05","min":30,"artId":122,"stageId":7},{"turnId":187,"startTime":"12:45","min":30,"artId":123,"stageId":7},{"turnId":188,"startTime":"13:25","min":45,"artId":124,"stageId":7},{"turnId":189,"startTime":"14:20","min":30,"artId":125,"stageId":7},{"turnId":190,"startTime":"15:00","min":30,"artId":126,"stageId":7},{"turnId":191,"startTime":"15:40","min":30,"artId":127,"stageId":7},{"turnId":192,"startTime":"16:20","min":25,"artId":128,"stageId":7,"collabArtList":[55,56],"title":"Road to TIF WINNER STAGE"},{"turnId":193,"startTime":"16:55","min":30,"artId":129,"stageId":7},{"turnId":194,"startTime":"18:10","min":40,"artId":130,"stageId":7},{"turnId":195,"startTime":"19:00","min":120,"artId":131,"stageId":7,"collabArtList":[16,27,86],"title":"ウラグランドフィナーレ"},{"turnId":196,"startTime":"11:00","min":30,"artId":132,"stageId":8},{"turnId":197,"startTime":"12:00","min":30,"artId":133,"stageId":8},{"turnId":198,"startTime":"13:00","min":30,"artId":134,"stageId":8},{"turnId":199,"startTime":"14:00","min":30,"artId":135,"stageId":8},{"turnId":200,"startTime":"15:00","min":30,"artId":136,"stageId":8},{"turnId":201,"startTime":"16:00","min":30,"artId":137,"stageId":8},{"turnId":202,"startTime":"17:00","min":30,"artId":138,"stageId":8},{"turnId":203,"startTime":"11:00","min":45,"artId":149,"stageId":9},{"turnId":204,"startTime":"12:00","min":45,"artId":80,"stageId":9},{"turnId":205,"startTime":"13:00","min":45,"artId":64,"stageId":9},{"turnId":206,"startTime":"14:30","min":45,"artId":153,"stageId":9},{"turnId":207,"startTime":"16:00","min":45,"artId":85,"stageId":9},{"turnId":208,"startTime":"18:00","min":45,"artId":83,"stageId":9},{"turnId":209,"startTime":"11:30","min":45,"artId":84,"stageId":10},{"turnId":210,"startTime":"14:30","min":45,"artId":147,"stageId":10},{"turnId":211,"startTime":"17:30","min":45,"artId":159,"stageId":10},{"turnId":212,"startTime":"12:00","min":45,"artId":142,"stageId":11},{"turnId":213,"startTime":"13:00","min":45,"artId":145,"stageId":11},{"turnId":214,"startTime":"14:00","min":45,"artId":157,"stageId":11},{"turnId":215,"startTime":"15:00","min":45,"artId":150,"stageId":11},{"turnId":216,"startTime":"16:00","min":45,"artId":144,"stageId":11},{"turnId":217,"startTime":"17:30","min":45,"artId":155,"stageId":11},{"turnId":218,"startTime":"11:00","min":45,"artId":152,"stageId":12},{"turnId":219,"startTime":"12:00","min":45,"artId":59,"stageId":12},{"turnId":220,"startTime":"14:00","min":45,"artId":140,"stageId":12},{"turnId":221,"startTime":"15:00","min":45,"artId":146,"stageId":12},{"turnId":222,"startTime":"17:00","min":45,"artId":154,"stageId":12},{"turnId":223,"startTime":"18:00","min":45,"artId":75,"stageId":12},{"turnId":224,"startTime":"12:30","min":45,"artId":77,"stageId":13,"wideWidth":2},{"turnId":225,"startTime":"15:00","min":45,"artId":143,"stageId":13},{"turnId":226,"startTime":"16:30","min":45,"artId":139,"stageId":13},{"turnId":227,"startTime":"12:30","min":0,"artId":77,"stageId":14},{"turnId":228,"startTime":"14:00","min":45,"artId":141,"stageId":14},{"turnId":229,"startTime":"15:00","min":45,"artId":151,"stageId":14},{"turnId":230,"startTime":"16:00","min":45,"artId":158,"stageId":14},{"turnId":231,"startTime":"17:00","min":45,"artId":73,"stageId":14},{"turnId":232,"startTime":"12:00","min":30,"artId":94,"stageId":15},{"turnId":233,"startTime":"14:45","min":45,"artId":19,"stageId":15},{"turnId":234,"startTime":"16:00","min":45,"artId":156,"stageId":15},{"turnId":235,"startTime":"17:00","min":45,"artId":107,"stageId":15},{"turnId":236,"startTime":"16:30","min":120,"artId":88,"stageId":92},{"turnId":237,"startTime":"15:00","min":75,"artId":38,"stageId":20},{"turnId":238,"startTime":"15:00","min":60,"artId":77,"stageId":86},{"turnId":239,"startTime":"13:30","min":90,"artId":56,"stageId":66},{"turnId":240,"startTime":"17:30","min":60,"artId":56,"stageId":66},{"turnId":241,"startTime":"17:15","min":90,"artId":94,"stageId":94},{"turnId":242,"startTime":"14:30","min":90,"artId":39,"stageId":62},{"turnId":243,"startTime":"18:30","min":90,"artId":39,"stageId":62},{"turnId":244,"startTime":"15:00","min":0,"artId":38,"stageId":20},{"turnId":245,"startTime":"15:00","min":75,"artId":31,"stageId":17},{"turnId":246,"startTime":"14:00","min":60,"artId":116,"stageId":119},{"turnId":247,"startTime":"17:30","min":75,"artId":116,"stageId":119},{"turnId":248,"startTime":"15:15","min":90,"artId":37,"stageId":21},{"turnId":249,"startTime":"12:30","min":90,"artId":62,"stageId":76},{"turnId":250,"startTime":"13:00","min":60,"artId":69,"stageId":38},{"turnId":251,"startTime":"10:00","min":120,"artId":82,"stageId":88},{"turnId":252,"startTime":"14:30","min":120,"artId":45,"stageId":37},{"turnId":253,"startTime":"14:00","min":90,"artId":12,"stageId":49},{"turnId":254,"startTime":"16:00","min":90,"artId":41,"stageId":34},{"turnId":255,"startTime":"12:00","min":90,"artId":17,"stageId":24},{"turnId":256,"startTime":"16:30","min":90,"artId":17,"stageId":24},{"turnId":257,"startTime":"14:00","min":90,"artId":86,"stageId":22},{"turnId":258,"startTime":"13:30","min":75,"artId":15,"stageId":53},{"turnId":259,"startTime":"17:30","min":60,"artId":15,"stageId":53},{"turnId":260,"startTime":"17:00","min":60,"artId":54,"stageId":19},{"turnId":261,"startTime":"12:00","min":90,"artId":44,"stageId":35,"title":"Onephony(無料集合写メ会)"},{"turnId":262,"startTime":"17:30","min":90,"artId":44,"stageId":35},{"turnId":263,"startTime":"14:00","min":90,"artId":104,"stageId":84},{"turnId":264,"startTime":"15:30","min":150,"artId":117,"stageId":120},{"turnId":265,"startTime":"12:30","min":90,"artId":96,"stageId":97},{"turnId":266,"startTime":"17:00","min":90,"artId":96,"stageId":97},{"turnId":267,"startTime":"12:45","min":75,"artId":20,"stageId":58},{"turnId":268,"startTime":"16:30","min":120,"artId":5,"stageId":32},{"turnId":269,"startTime":"17:00","min":0,"artId":54,"stageId":19},{"turnId":270,"startTime":"13:00","min":90,"artId":78,"stageId":85},{"turnId":271,"startTime":"18:05","min":40,"artId":78,"stageId":85},{"turnId":272,"startTime":"12:30","min":45,"artId":162,"stageId":10},{"turnId":273,"startTime":"13:30","min":60,"artId":163,"stageId":10},{"turnId":274,"startTime":"11:15","min":45,"artId":63,"stageId":13},{"turnId":275,"startTime":"13:45","min":15,"artId":164,"stageId":13},{"turnId":276,"startTime":"13:45","min":15,"artId":165,"stageId":15},{"turnId":277,"startTime":"13:45","min":15,"artId":166,"stageId":16},{"turnId":278,"startTime":"14:45","min":15,"artId":167,"stageId":16},{"turnId":279,"startTime":"15:45","min":15,"artId":168,"stageId":16},{"turnId":280,"startTime":"16:45","min":15,"artId":169,"stageId":16},{"turnId":281,"startTime":"17:45","min":15,"artId":170,"stageId":16},{"turnId":282,"startTime":"16:30","min":0,"artId":69,"stageId":27},{"turnId":283,"startTime":"16:00","min":120,"artId":13,"stageId":52},{"turnId":284,"startTime":"12:00","min":120,"artId":6,"stageId":36},{"turnId":285,"startTime":"11:30","min":30,"artId":21,"stageId":110,"title":"i-COL(レギュレーション制限あり)"},{"turnId":286,"startTime":"12:30","min":60,"artId":36,"stageId":113},{"turnId":287,"startTime":"13:30","min":60,"artId":119,"stageId":116},{"turnId":288,"startTime":"14:20","min":60,"artId":24,"stageId":111},{"turnId":289,"startTime":"14:40","min":60,"artId":93,"stageId":115},{"turnId":290,"startTime":"16:20","min":60,"artId":26,"stageId":112},{"turnId":291,"startTime":"16:40","min":60,"artId":89,"stageId":114},{"turnId":292,"startTime":"16:00","min":75,"artId":14,"stageId":105},{"turnId":293,"startTime":"10:00","min":90,"artId":58,"stageId":23},{"turnId":294,"startTime":"15:00","min":55,"artId":84,"stageId":90},{"turnId":295,"startTime":"17:20","min":85,"artId":84,"stageId":90},{"turnId":296,"startTime":"12:25","min":115,"artId":53,"stageId":70},{"turnId":297,"startTime":"17:05","min":100,"artId":53,"stageId":70},{"turnId":298,"startTime":"16:30","min":90,"artId":80,"stageId":48},{"turnId":299,"startTime":"11:00","min":60,"artId":108,"stageId":101},{"turnId":300,"startTime":"14:45","min":30,"artId":108,"stageId":101,"title":"衛星とカラテア(無料ハイタッチ会)"},{"turnId":301,"startTime":"16:30","min":60,"artId":105,"stageId":74},{"turnId":302,"startTime":"15:00","min":90,"artId":64,"stageId":18},{"turnId":303,"startTime":"16:20","min":60,"artId":59,"stageId":75},{"turnId":304,"startTime":"16:30","min":50,"artId":50,"stageId":69},{"turnId":305,"startTime":"13:30","min":105,"artId":112,"stageId":57},{"turnId":306,"startTime":"13:00","min":90,"artId":19,"stageId":55},{"turnId":307,"startTime":"17:50","min":40,"artId":19,"stageId":55},{"turnId":308,"startTime":"12:30","min":90,"artId":110,"stageId":103},{"turnId":309,"startTime":"16:00","min":90,"artId":110,"stageId":103},{"turnId":310,"startTime":"12:30","min":90,"artId":33,"stageId":56},{"turnId":311,"startTime":"17:00","min":45,"artId":33,"stageId":56},{"turnId":312,"startTime":"14:00","min":180,"artId":97,"stageId":98},{"turnId":313,"startTime":"15:15","min":90,"artId":18,"stageId":106},{"turnId":314,"startTime":"18:00","min":45,"artId":18,"stageId":106},{"turnId":315,"startTime":"15:15","min":60,"artId":30,"stageId":107},{"turnId":316,"startTime":"12:30","min":90,"artId":83,"stageId":89},{"turnId":317,"startTime":"17:00","min":60,"artId":9,"stageId":39},{"turnId":318,"startTime":"15:30","min":90,"artId":46,"stageId":65},{"turnId":319,"startTime":"15:30","min":60,"artId":11,"stageId":25,"wideWidth":4},{"turnId":320,"startTime":"16:30","min":60,"artId":81,"stageId":27},{"turnId":321,"startTime":"15:30","min":0,"artId":71,"stageId":73,"wideWidth":2},{"turnId":322,"startTime":"10:00","min":40,"artId":90,"stageId":78,"title":"なみだ色の消しごむ(10:00〜12:10グッズ販売)"},{"turnId":323,"startTime":"10:40","min":90,"artId":90,"stageId":78},{"turnId":324,"startTime":"13:30","min":60,"artId":98,"stageId":26},{"turnId":325,"startTime":"15:30","min":195,"artId":51,"stageId":72,"collabArtList":[51,71],"wideWidth":2},{"turnId":326,"startTime":"14:15","min":85,"artId":68,"stageId":121},{"turnId":327,"startTime":"13:45","min":60,"artId":118,"stageId":28},{"turnId":328,"startTime":"16:00","min":60,"artId":63,"stageId":77},{"turnId":329,"startTime":"11:30","min":30,"artId":27,"stageId":45,"title":"JamsCollection(販売開始)"},{"turnId":330,"startTime":"12:00","min":60,"artId":27,"stageId":45,"title":"JamsCollection(保科・村望・北乃・花坂)"},{"turnId":331,"startTime":"13:00","min":60,"artId":27,"stageId":45,"title":"JamsCollection(津代・水瀬・小此木)"},{"turnId":332,"startTime":"15:45","min":45,"artId":95,"stageId":96},{"turnId":333,"startTime":"15:30","min":0,"artId":11,"stageId":25},{"turnId":334,"startTime":"13:00","min":90,"artId":16,"stageId":44},{"turnId":335,"startTime":"12:00","min":0,"artId":6,"stageId":36},{"turnId":336,"startTime":"16:00","min":90,"artId":76,"stageId":83},{"turnId":337,"startTime":"12:30","min":60,"artId":171,"stageId":122,"title":"Ange☆Reve(城崎桃華・初季｡E1~4)"},{"turnId":338,"startTime":"16:30","min":45,"artId":171,"stageId":122,"title":"Ange☆Reve(城崎桃華・初季｡E1~4)"},{"turnId":339,"startTime":"14:00","min":115,"artId":47,"stageId":67},{"turnId":340,"startTime":"13:30","min":90,"artId":113,"stageId":117},{"turnId":341,"startTime":"15:45","min":0,"artId":95,"stageId":96},{"turnId":342,"startTime":"17:30","min":75,"artId":113,"stageId":117},{"turnId":343,"startTime":"12:30","min":90,"artId":35,"stageId":61},{"turnId":344,"startTime":"15:15","min":0,"artId":37,"stageId":21},{"turnId":345,"startTime":"12:45","min":60,"artId":75,"stageId":82},{"turnId":346,"startTime":"15:00","min":60,"artId":75,"stageId":82},{"turnId":347,"startTime":"14:10","min":140,"artId":74,"stageId":80},{"turnId":348,"startTime":"11:30","min":90,"artId":1,"stageId":30},{"turnId":349,"startTime":"16:00","min":0,"artId":76,"stageId":83},{"turnId":350,"startTime":"13:30","min":90,"artId":0,"stageId":29},{"turnId":351,"startTime":"12:25","min":60,"artId":55,"stageId":79},{"turnId":352,"startTime":"17:00","min":70,"artId":55,"stageId":79},{"turnId":353,"startTime":"13:30","min":60,"artId":92,"stageId":93},{"turnId":354,"startTime":"15:30","min":60,"artId":34,"stageId":60},{"turnId":355,"startTime":"11:00","min":30,"artId":94,"stageId":94},{"turnId":356,"startTime":"14:00","min":60,"artId":40,"stageId":63},{"turnId":357,"startTime":"17:45","min":60,"artId":40,"stageId":63},{"turnId":358,"startTime":"17:00","min":105,"artId":92,"stageId":93},{"turnId":359,"startTime":"16:30","min":90,"artId":69,"stageId":38},{"turnId":360,"startTime":"14:00","min":60,"artId":160,"stageId":47},{"turnId":361,"startTime":"10:00","min":450,"artId":8,"stageId":43},{"turnId":362,"startTime":"15:40","min":70,"artId":107,"stageId":46},{"turnId":363,"startTime":"11:50","min":60,"artId":57,"stageId":71},{"turnId":364,"startTime":"17:55","min":60,"artId":57,"stageId":71},{"turnId":365,"startTime":"11:00","min":60,"artId":73,"stageId":81},{"turnId":366,"startTime":"12:00","min":60,"artId":73,"stageId":81},{"turnId":367,"startTime":"13:00","min":90,"artId":85,"stageId":91},{"turnId":368,"startTime":"14:30","min":60,"artId":100,"stageId":100}]}