{"liveId":448,"jsonVersion":9,"openTime":"12","closeTime":"23","notificationVersion":"2","notification":"・ライブのタイテを登録しました(8/11時点)\n・MCについては省略しています\n・無料と有料の会場があるのでご注意ください\n・申し訳ありませんが今回の特典会タイテは対応できかねます｡ユーザご自身で枠を追加できる機能がありますのでご活用ください｡","artList":[{"artId":0,"name":"82回目の終身刑(band)"},{"artId":1,"name":"BOCCHI。"},{"artId":2,"name":"Beloved"},{"artId":3,"name":"CLEAR'S"},{"artId":4,"name":"Cent Heaven"},{"artId":5,"name":"Ceui"},{"artId":6,"name":"ESTLINK☆"},{"artId":7,"name":"Ep:ChouChou"},{"artId":8,"name":"FLAPSTAR"},{"artId":9,"name":"HAPPY CREATORS"},{"artId":10,"name":"KRD8"},{"artId":11,"name":"LOTUS MARRY"},{"artId":12,"name":"MATANAGOYA"},{"artId":13,"name":"MOSAIC.WAV"},{"artId":14,"name":"Maison de Queen"},{"artId":15,"name":"NO❤︎AF"},{"artId":16,"name":"Nine chocolates"},{"artId":17,"name":"PLYDE"},{"artId":18,"name":"PULSAR_CLIMAX"},{"artId":19,"name":"ROSARIO+CROSS"},{"artId":20,"name":"Ramu'z"},{"artId":21,"name":"SITRA."},{"artId":22,"name":"SUPER☆GiRLS"},{"artId":23,"name":"SnowComp/ex"},{"artId":24,"name":"Star☆T"},{"artId":25,"name":"Stella!"},{"artId":26,"name":"Stellagrima＊"},{"artId":27,"name":"THE POWER"},{"artId":28,"name":"Tama (ex. Hysteric Blue)"},{"artId":29,"name":"ULTRA-PRISM"},{"artId":30,"name":"Veronica"},{"artId":31,"name":"ZooZooZoo"},{"artId":32,"name":"d-girls"},{"artId":33,"name":"iSPY"},{"artId":34,"name":"meluQ"},{"artId":35,"name":"mofu/mofu"},{"artId":36,"name":"no Filter"},{"artId":37,"name":"pipia"},{"artId":38,"name":"あすとりーのうさぎ"},{"artId":39,"name":"あたまのなかは8ビット⁉︎"},{"artId":40,"name":"おちゃメンタル☆パーティー"},{"artId":41,"name":"お願い‼︎フルハウス"},{"artId":42,"name":"きゅーんず！"},{"artId":43,"name":"にっぽんワチャチャ"},{"artId":44,"name":"ふぁんたす！"},{"artId":45,"name":"まりえ(44)"},{"artId":46,"name":"ゆるめるモ！"},{"artId":47,"name":"わちゃめちゃ！"},{"artId":48,"name":"アイドルカレッジ"},{"artId":49,"name":"アステリア"},{"artId":50,"name":"キミだけの花言葉"},{"artId":51,"name":"ナト☆カン"},{"artId":52,"name":"バンドじゃないもん！MAXX NAKAYOSHI"},{"artId":53,"name":"ミニワチャ"},{"artId":54,"name":"ミリオン！~ Million Heaven Tokyo ~"},{"artId":55,"name":"メリーミューズ"},{"artId":56,"name":"三谷綾子"},{"artId":57,"name":"下川みくに"},{"artId":58,"name":"世界で1番シンデレラ"},{"artId":59,"name":"刹那"},{"artId":60,"name":""},{"artId":61,"name":"夜宙☆ShiNew'"},{"artId":62,"name":"彩羽真矢"},{"artId":63,"name":"彩音"},{"artId":64,"name":"恋セ界"},{"artId":65,"name":"愛※ぱんでみっく！"},{"artId":66,"name":"愛内里菜"},{"artId":67,"name":"成瀬瑛美(ex.でんぱ組.inc)"},{"artId":68,"name":""},{"artId":69,"name":"戦国アニマル極楽浄土"},{"artId":70,"name":"月宵◇クレシェンテ"},{"artId":71,"name":""},{"artId":72,"name":"有栖川雛姫"},{"artId":73,"name":"未完成のキャラメル"},{"artId":74,"name":"松澤由実"},{"artId":75,"name":"桃井はるこ"},{"artId":76,"name":"煌めき☆アンフォレント"},{"artId":77,"name":"究極人形"},{"artId":78,"name":"葉月"},{"artId":79,"name":"輝きぱにっく"},{"artId":80,"name":"鈴原優美"},{"artId":81,"name":"鈴木Mob."}],"stageList":[{"stageId":0,"stageName":"無料: NAGOYA ReNY limited","stageNameShort":"無料: NAGOYA ReNY limited","colorName":"stage-red"},{"stageId":1,"stageName":"無料: X-HALL","stageNameShort":"無料: X-HALL","colorName":"stage-green"},{"stageId":2,"stageName":"無料: RADHALL","stageNameShort":"無料: RADHALL","colorName":"stage-purple"},{"stageId":3,"stageName":"有料: Zephyr Hall","stageNameShort":"有料: Zephyr Hall","colorName":"stage-orange"},{"stageId":4,"stageName":"有料: Lion theater","stageNameShort":"有料: Lion theater","colorName":"stage-blue"},{"stageId":5,"stageName":"有料: Lion Café","stageNameShort":"有料: Lion Café","colorName":"stage-yellow"},{"stageId":6,"stageName":"有料: Dt.BLD3F","stageNameShort":"有料: Dt.BLD3F","colorName":"stage-teal"},{"stageId":7,"stageName":"有料: Dt.BLD2F","stageNameShort":"有料: Dt.BLD2F","colorName":"stage-pink"}],"turnList":[{"turnId":0,"startTime":"13:15","min":20,"artId":67,"stageId":0},{"turnId":1,"startTime":"13:35","min":20,"artId":5,"stageId":0},{"turnId":2,"startTime":"14:05","min":20,"artId":13,"stageId":0},{"turnId":3,"startTime":"14:30","min":20,"artId":9,"stageId":0},{"turnId":4,"startTime":"14:50","min":20,"artId":43,"stageId":0},{"turnId":5,"startTime":"15:10","min":20,"artId":36,"stageId":0},{"turnId":6,"startTime":"15:30","min":20,"artId":10,"stageId":0},{"turnId":7,"startTime":"15:50","min":20,"artId":40,"stageId":0},{"turnId":8,"startTime":"16:10","min":20,"artId":69,"stageId":0},{"turnId":9,"startTime":"16:30","min":20,"artId":1,"stageId":0},{"turnId":10,"startTime":"16:50","min":20,"artId":54,"stageId":0},{"turnId":11,"startTime":"17:15","min":20,"artId":61,"stageId":0},{"turnId":12,"startTime":"17:35","min":20,"artId":26,"stageId":0},{"turnId":13,"startTime":"17:55","min":20,"artId":70,"stageId":0},{"turnId":14,"startTime":"18:15","min":20,"artId":48,"stageId":0},{"turnId":15,"startTime":"18:35","min":20,"artId":14,"stageId":0},{"turnId":16,"startTime":"18:55","min":25,"artId":22,"stageId":0},{"turnId":17,"startTime":"19:20","min":25,"artId":76,"stageId":0},{"turnId":18,"startTime":"20:00","min":30,"artId":52,"stageId":0},{"turnId":19,"startTime":"12:55","min":20,"artId":46,"stageId":1},{"turnId":20,"startTime":"13:15","min":20,"artId":62,"stageId":1},{"turnId":21,"startTime":"13:35","min":20,"artId":59,"stageId":1},{"turnId":22,"startTime":"13:55","min":20,"artId":42,"stageId":1},{"turnId":23,"startTime":"14:15","min":20,"artId":16,"stageId":1},{"turnId":24,"startTime":"14:35","min":20,"artId":35,"stageId":1},{"turnId":25,"startTime":"14:55","min":20,"artId":6,"stageId":1},{"turnId":26,"startTime":"15:15","min":20,"artId":2,"stageId":1},{"turnId":27,"startTime":"15:35","min":20,"artId":32,"stageId":1},{"turnId":28,"startTime":"16:00","min":20,"artId":74,"stageId":1},{"turnId":29,"startTime":"16:20","min":20,"artId":25,"stageId":1},{"turnId":30,"startTime":"16:40","min":20,"artId":33,"stageId":1},{"turnId":31,"startTime":"17:00","min":20,"artId":34,"stageId":1},{"turnId":32,"startTime":"17:20","min":20,"artId":41,"stageId":1},{"turnId":33,"startTime":"17:40","min":20,"artId":19,"stageId":1},{"turnId":34,"startTime":"18:00","min":20,"artId":73,"stageId":1},{"turnId":35,"startTime":"18:20","min":20,"artId":4,"stageId":1},{"turnId":36,"startTime":"18:45","min":20,"artId":24,"stageId":1},{"turnId":37,"startTime":"19:05","min":20,"artId":39,"stageId":1},{"turnId":38,"startTime":"19:25","min":20,"artId":8,"stageId":1},{"turnId":39,"startTime":"19:45","min":20,"artId":45,"stageId":1},{"turnId":40,"startTime":"20:05","min":20,"artId":12,"stageId":1},{"turnId":41,"startTime":"13:15","min":15,"artId":58,"stageId":2},{"turnId":42,"startTime":"13:30","min":15,"artId":72,"stageId":2},{"turnId":43,"startTime":"13:45","min":15,"artId":27,"stageId":2},{"turnId":44,"startTime":"14:00","min":15,"artId":53,"stageId":2},{"turnId":45,"startTime":"14:15","min":15,"artId":79,"stageId":2},{"turnId":46,"startTime":"14:30","min":15,"artId":21,"stageId":2},{"turnId":47,"startTime":"14:45","min":15,"artId":20,"stageId":2},{"turnId":48,"startTime":"15:05","min":15,"artId":47,"stageId":2},{"turnId":49,"startTime":"15:20","min":15,"artId":31,"stageId":2},{"turnId":50,"startTime":"15:35","min":15,"artId":3,"stageId":2},{"turnId":51,"startTime":"15:50","min":20,"artId":18,"stageId":2},{"turnId":52,"startTime":"16:10","min":15,"artId":15,"stageId":2},{"turnId":53,"startTime":"16:25","min":15,"artId":17,"stageId":2},{"turnId":54,"startTime":"16:40","min":20,"artId":23,"stageId":2},{"turnId":55,"startTime":"17:00","min":15,"artId":55,"stageId":2},{"turnId":56,"startTime":"17:15","min":20,"artId":11,"stageId":2},{"turnId":57,"startTime":"17:35","min":15,"artId":30,"stageId":2},{"turnId":58,"startTime":"17:50","min":15,"artId":65,"stageId":2},{"turnId":59,"startTime":"18:10","min":15,"artId":37,"stageId":2},{"turnId":60,"startTime":"18:25","min":15,"artId":44,"stageId":2},{"turnId":61,"startTime":"18:40","min":15,"artId":7,"stageId":2},{"turnId":62,"startTime":"18:55","min":15,"artId":50,"stageId":2},{"turnId":63,"startTime":"19:10","min":20,"artId":38,"stageId":2},{"turnId":64,"startTime":"19:45","min":25,"artId":0,"stageId":2},{"turnId":65,"startTime":"20:25","min":15,"artId":64,"stageId":2},{"turnId":66,"startTime":"20:40","min":20,"artId":49,"stageId":2},{"turnId":67,"startTime":"21:00","min":20,"artId":77,"stageId":2},{"turnId":68,"startTime":"21:20","min":20,"artId":51,"stageId":2},{"turnId":69,"startTime":"14:30","min":15,"artId":56,"stageId":3},{"turnId":70,"startTime":"14:45","min":15,"artId":81,"stageId":3},{"turnId":71,"startTime":"15:05","min":25,"artId":57,"stageId":3},{"turnId":72,"startTime":"15:30","min":25,"artId":48,"stageId":3},{"turnId":73,"startTime":"15:55","min":25,"artId":22,"stageId":3},{"turnId":74,"startTime":"16:20","min":25,"artId":76,"stageId":3},{"turnId":75,"startTime":"16:45","min":20,"artId":62,"stageId":3},{"turnId":76,"startTime":"17:05","min":25,"artId":5,"stageId":3},{"turnId":77,"startTime":"17:30","min":25,"artId":74,"stageId":3},{"turnId":78,"startTime":"17:55","min":20,"artId":67,"stageId":3},{"turnId":79,"startTime":"18:25","min":25,"artId":29,"stageId":3},{"turnId":80,"startTime":"19:00","min":25,"artId":13,"stageId":3},{"turnId":81,"startTime":"19:30","min":25,"artId":28,"stageId":3},{"turnId":82,"startTime":"19:55","min":25,"artId":66,"stageId":3},{"turnId":83,"startTime":"20:20","min":25,"artId":63,"stageId":3},{"turnId":84,"startTime":"20:45","min":25,"artId":75,"stageId":3},{"turnId":85,"startTime":"12:55","min":20,"artId":45,"stageId":4},{"turnId":86,"startTime":"13:15","min":20,"artId":54,"stageId":4},{"turnId":87,"startTime":"13:35","min":20,"artId":69,"stageId":4},{"turnId":88,"startTime":"13:55","min":20,"artId":24,"stageId":4},{"turnId":89,"startTime":"14:15","min":20,"artId":19,"stageId":4},{"turnId":90,"startTime":"14:35","min":20,"artId":26,"stageId":4},{"turnId":91,"startTime":"14:55","min":20,"artId":70,"stageId":4},{"turnId":92,"startTime":"15:15","min":20,"artId":61,"stageId":4},{"turnId":93,"startTime":"15:35","min":20,"artId":14,"stageId":4},{"turnId":94,"startTime":"16:00","min":20,"artId":39,"stageId":4},{"turnId":95,"startTime":"16:20","min":20,"artId":12,"stageId":4},{"turnId":96,"startTime":"16:40","min":20,"artId":49,"stageId":4},{"turnId":97,"startTime":"17:00","min":20,"artId":77,"stageId":4},{"turnId":98,"startTime":"17:20","min":20,"artId":16,"stageId":4},{"turnId":99,"startTime":"17:40","min":20,"artId":51,"stageId":4},{"turnId":100,"startTime":"18:00","min":20,"artId":6,"stageId":4},{"turnId":101,"startTime":"18:25","min":20,"artId":2,"stageId":4},{"turnId":102,"startTime":"18:45","min":20,"artId":10,"stageId":4},{"turnId":103,"startTime":"19:05","min":20,"artId":40,"stageId":4},{"turnId":104,"startTime":"19:25","min":20,"artId":33,"stageId":4},{"turnId":105,"startTime":"19:45","min":20,"artId":1,"stageId":4},{"turnId":106,"startTime":"20:05","min":20,"artId":36,"stageId":4},{"turnId":107,"startTime":"20:25","min":20,"artId":41,"stageId":4},{"turnId":108,"startTime":"16:40","min":20,"artId":78,"stageId":5},{"turnId":109,"startTime":"17:00","min":20,"artId":80,"stageId":5},{"turnId":110,"startTime":"17:20","min":20,"artId":59,"stageId":5},{"turnId":111,"startTime":"17:50","min":20,"artId":27,"stageId":5},{"turnId":112,"startTime":"18:10","min":20,"artId":53,"stageId":5},{"turnId":113,"startTime":"18:30","min":20,"artId":3,"stageId":5},{"turnId":114,"startTime":"19:00","min":20,"artId":15,"stageId":5},{"turnId":115,"startTime":"19:20","min":20,"artId":9,"stageId":5},{"turnId":116,"startTime":"19:40","min":20,"artId":34,"stageId":5},{"turnId":117,"startTime":"20:10","min":20,"artId":11,"stageId":5},{"turnId":118,"startTime":"20:30","min":20,"artId":25,"stageId":5},{"turnId":119,"startTime":"20:50","min":20,"artId":4,"stageId":5},{"turnId":120,"startTime":"16:00","min":20,"artId":44,"stageId":6},{"turnId":121,"startTime":"16:20","min":20,"artId":7,"stageId":6},{"turnId":122,"startTime":"16:40","min":20,"artId":38,"stageId":6},{"turnId":123,"startTime":"17:00","min":20,"artId":64,"stageId":6},{"turnId":124,"startTime":"17:25","min":20,"artId":79,"stageId":6},{"turnId":125,"startTime":"17:45","min":20,"artId":47,"stageId":6},{"turnId":126,"startTime":"18:05","min":20,"artId":20,"stageId":6},{"turnId":127,"startTime":"18:25","min":20,"artId":21,"stageId":6},{"turnId":128,"startTime":"19:55","min":20,"artId":17,"stageId":6},{"turnId":129,"startTime":"20:15","min":20,"artId":35,"stageId":6},{"turnId":130,"startTime":"20:35","min":20,"artId":55,"stageId":6},{"turnId":131,"startTime":"20:55","min":20,"artId":30,"stageId":6},{"turnId":132,"startTime":"16:30","min":20,"artId":50,"stageId":7},{"turnId":133,"startTime":"16:50","min":20,"artId":8,"stageId":7},{"turnId":134,"startTime":"17:10","min":20,"artId":72,"stageId":7},{"turnId":135,"startTime":"17:40","min":20,"artId":58,"stageId":7},{"turnId":136,"startTime":"18:00","min":20,"artId":31,"stageId":7},{"turnId":137,"startTime":"18:20","min":20,"artId":32,"stageId":7},{"turnId":138,"startTime":"19:50","min":20,"artId":18,"stageId":7},{"turnId":139,"startTime":"20:10","min":20,"artId":23,"stageId":7},{"turnId":140,"startTime":"20:30","min":20,"artId":37,"stageId":7},{"turnId":141,"startTime":"20:50","min":20,"artId":65,"stageId":7}]}
