{"liveId":366,"jsonVersion":1,"openTime":"10","closeTime":"23","notificationVersion":"1","notification":"","artList":[{"artId":0,"name":"10-FEET"},{"artId":1,"name":"ASIAN KUNG-FU GENERATION"},{"artId":2,"name":"Aooo"},{"artId":3,"name":"BEGIN × シアターブルック"},{"artId":4,"name":"BRAHMAN"},{"artId":5,"name":"Crossfaith"},{"artId":6,"name":"ELLEGARDEN"},{"artId":7,"name":"G-FREAK FACTORY Guest: TAKUMA(10-FEET) TOSHI-LOW(BRAHMAN)"},{"artId":8,"name":"HEY-SMITH"},{"artId":9,"name":"Hakubi × UNFAIR RULE"},{"artId":10,"name":"I Don't Like Mondays. Guest:後日発表"},{"artId":11,"name":"KALMA"},{"artId":12,"name":"Kroi"},{"artId":13,"name":"MAN WITH A MISSION"},{"artId":14,"name":"PEDRO × サバシスター"},{"artId":15,"name":"Rei"},{"artId":16,"name":"SAKANAMON Guest:たかはしほのか(リーガルリリー) 田辺由明(マカロニえんぴつ)"},{"artId":17,"name":"SiM"},{"artId":18,"name":"THE COLLECTORS × フラワーカンパニーズ Guest:田中ヤコブ(家主)"},{"artId":19,"name":"THE SPELLBOUND"},{"artId":20,"name":"WANDS Guest:ナヲ(マキシマム・ザ・ホルモン)"},{"artId":21,"name":"ZAZEN BOYS"},{"artId":22,"name":"eastern youth"},{"artId":23,"name":"indigo la End"},{"artId":24,"name":"muque"},{"artId":25,"name":"reGretGirl"},{"artId":26,"name":"toe"},{"artId":27,"name":"yutori"},{"artId":28,"name":"おとどけチータくん 高速バンド"},{"artId":29,"name":"みちのくプロレス"},{"artId":30,"name":"サニーデイ・サービス Guest:GLIM SPANKY"},{"artId":31,"name":"トンボコープ"},{"artId":32,"name":"ハンブレッダーズ"},{"artId":33,"name":"マカロニえんぴつ"},{"artId":34,"name":"マキシマム ザ ホルモン"},{"artId":35,"name":"友成空"},{"artId":36,"name":"四星球"},{"artId":37,"name":"夢弦会(津軽三味線)"},{"artId":38,"name":"大橋ちっぽけ"},{"artId":39,"name":"川内太鼓"},{"artId":40,"name":"川崎中学校吹奏楽部"},{"artId":41,"name":"東京スカパラダイスオーケストラ Guest:後日発表"},{"artId":42,"name":"由薫×ルイ"},{"artId":43,"name":"百々和宏と69ers"},{"artId":44,"name":"羊文学"},{"artId":45,"name":"藤原美幸(秋田民謡)"},{"artId":46,"name":"西馬音内盆踊り"},{"artId":47,"name":"黒夢"}],"stageList":[{"stageId":0,"stageName":"MICHINOKU","stageNameShort":"MICHINOKU","colorName":"stage-orange"},{"stageId":1,"stageName":"ARAHABAKI","stageNameShort":"ARAHABAKI","colorName":"stage-purple"},{"stageId":2,"stageName":"HATAHATA","stageNameShort":"HATAHATA","colorName":"stage-red"},{"stageId":3,"stageName":"TSUGARU","stageNameShort":"TSUGARU","colorName":"stage-yellow"},{"stageId":4,"stageName":"HANAGASA","stageNameShort":"HANAGASA","colorName":"stage-grey"},{"stageId":5,"stageName":"BAN-ETSU","stageNameShort":"BAN-ETSU","colorName":"stage-cyan"},{"stageId":6,"stageName":"東北ライブハウス大作戦STAGE","stageNameShort":"東北ライブハウス大作戦STAGE","colorName":"stage-blue"}],"turnList":[{"turnId":0,"startTime":"11:00","min":20,"artId":40,"stageId":0},{"turnId":1,"startTime":"12:00","min":45,"artId":0,"stageId":0},{"turnId":2,"startTime":"13:30","min":45,"artId":34,"stageId":0},{"turnId":3,"startTime":"15:00","min":45,"artId":1,"stageId":0},{"turnId":4,"startTime":"16:30","min":45,"artId":6,"stageId":0},{"turnId":5,"startTime":"18:15","min":45,"artId":4,"stageId":0},{"turnId":6,"startTime":"20:00","min":75,"artId":13,"stageId":0},{"turnId":7,"startTime":"11:00","min":50,"artId":9,"stageId":1},{"turnId":8,"startTime":"12:30","min":30,"artId":25,"stageId":1},{"turnId":9,"startTime":"13:40","min":40,"artId":10,"stageId":1},{"turnId":10,"startTime":"15:20","min":60,"artId":14,"stageId":1},{"turnId":11,"startTime":"17:20","min":60,"artId":18,"stageId":1},{"turnId":12,"startTime":"18:50","min":15,"artId":39,"stageId":1},{"turnId":13,"startTime":"19:15","min":40,"artId":11,"stageId":1},{"turnId":14,"startTime":"11:30","min":10,"artId":45,"stageId":2},{"turnId":15,"startTime":"11:50","min":30,"artId":27,"stageId":2},{"turnId":16,"startTime":"12:55","min":35,"artId":8,"stageId":2},{"turnId":17,"startTime":"13:30","min":30,"artId":29,"stageId":2},{"turnId":18,"startTime":"14:15","min":40,"artId":7,"stageId":2},{"turnId":19,"startTime":"14:55","min":35,"artId":29,"stageId":2},{"turnId":20,"startTime":"15:45","min":35,"artId":47,"stageId":2},{"turnId":21,"startTime":"16:20","min":20,"artId":46,"stageId":2},{"turnId":22,"startTime":"17:20","min":35,"artId":5,"stageId":2},{"turnId":23,"startTime":"17:55","min":20,"artId":46,"stageId":2},{"turnId":24,"startTime":"19:00","min":40,"artId":17,"stageId":2},{"turnId":25,"startTime":"11:40","min":30,"artId":31,"stageId":3},{"turnId":26,"startTime":"13:10","min":40,"artId":16,"stageId":3},{"turnId":27,"startTime":"14:45","min":60,"artId":3,"stageId":3},{"turnId":28,"startTime":"16:40","min":35,"artId":22,"stageId":3},{"turnId":29,"startTime":"18:00","min":10,"artId":37,"stageId":3},{"turnId":30,"startTime":"18:15","min":45,"artId":30,"stageId":3},{"turnId":31,"startTime":"19:40","min":10,"artId":37,"stageId":3},{"turnId":32,"startTime":"19:55","min":35,"artId":44,"stageId":3},{"turnId":33,"startTime":"11:00","min":30,"artId":2,"stageId":4},{"turnId":34,"startTime":"12:20","min":40,"artId":15,"stageId":4},{"turnId":35,"startTime":"14:00","min":30,"artId":24,"stageId":4},{"turnId":36,"startTime":"15:55","min":35,"artId":19,"stageId":4},{"turnId":37,"startTime":"17:25","min":35,"artId":26,"stageId":4},{"turnId":38,"startTime":"19:05","min":35,"artId":21,"stageId":4},{"turnId":39,"startTime":"20:40","min":35,"artId":12,"stageId":4},{"turnId":40,"startTime":"11:00","min":45,"artId":36,"stageId":5},{"turnId":41,"startTime":"12:40","min":45,"artId":23,"stageId":5},{"turnId":42,"startTime":"14:05","min":45,"artId":32,"stageId":5},{"turnId":43,"startTime":"15:40","min":45,"artId":20,"stageId":5},{"turnId":44,"startTime":"17:15","min":45,"artId":33,"stageId":5},{"turnId":45,"startTime":"18:55","min":45,"artId":41,"stageId":5},{"turnId":46,"startTime":"10:30","min":30,"artId":28,"stageId":6},{"turnId":47,"startTime":"11:55","min":40,"artId":42,"stageId":6},{"turnId":48,"startTime":"13:10","min":30,"artId":38,"stageId":6},{"turnId":49,"startTime":"14:50","min":30,"artId":35,"stageId":6},{"turnId":50,"startTime":"16:30","min":45,"artId":43,"stageId":6}]}