{"liveId":322,"jsonVersion":1,"openTime":"11","closeTime":"23","notificationVersion":"2","notification":"公式タイテ変更(9/30)に対応しました","artList":[{"artId":0,"name":"鉄風東京"},{"artId":1,"name":"YUTORI-SEDAI"},{"artId":2,"name":"TRACK15"},{"artId":3,"name":"眉村ちあき"},{"artId":4,"name":"FIVE NEW OLD"},{"artId":5,"name":"Conton Candy"},{"artId":6,"name":"レトロリロン"},{"artId":7,"name":"チョーキューメイ"},{"artId":8,"name":"PK shampoo"},{"artId":9,"name":"シャイトープ"},{"artId":10,"name":"Cloudy（オーディショングランプリ）"},{"artId":11,"name":"カメレオン・ライム・ウーピーパイ"},{"artId":12,"name":"ポップしないで"},{"artId":13,"name":"MAYSON's PARTY"},{"artId":14,"name":"muque"},{"artId":15,"name":"G over"},{"artId":16,"name":"Mega Shinnosuke"},{"artId":17,"name":"ルサンチマン"},{"artId":18,"name":"Laughing Hick"},{"artId":19,"name":"Bocchi"},{"artId":20,"name":"YAJICO GIRL"},{"artId":21,"name":"BILLY BOO"},{"artId":22,"name":"ANTENA"},{"artId":23,"name":"LET ME KNOW"},{"artId":24,"name":"Dannie May"},{"artId":25,"name":"Risky Melody"},{"artId":26,"name":"Drop After Dawn"},{"artId":27,"name":"CLAN QUEEN"},{"artId":28,"name":"空白ごっこ"},{"artId":29,"name":"RiL"},{"artId":30,"name":"COPES"},{"artId":31,"name":"Tyrkouaz"},{"artId":32,"name":"HwyI"},{"artId":33,"name":"月追う彼方"},{"artId":34,"name":"tonari."},{"artId":35,"name":"pachae"},{"artId":36,"name":"古墳シスターズ"},{"artId":37,"name":"omeme tenten"},{"artId":38,"name":"GLASGOW"},{"artId":39,"name":"Umisaya"},{"artId":40,"name":"アスノポラリス"},{"artId":41,"name":"ちゃくら"},{"artId":42,"name":"ガラクタ"},{"artId":43,"name":"UNFAIR RULE"},{"artId":44,"name":"WENDY"},{"artId":45,"name":"anewhite"},{"artId":46,"name":"KOHAKU"},{"artId":47,"name":"浪漫革命"},{"artId":48,"name":"JIJIM"},{"artId":49,"name":"リュベンス"},{"artId":50,"name":"Apes"},{"artId":51,"name":"ジ・エンプティ"},{"artId":52,"name":"luv"},{"artId":53,"name":"EYRIE"},{"artId":54,"name":"カラノア"},{"artId":55,"name":"TOSH"},{"artId":56,"name":"BOYLEKUWAI"},{"artId":57,"name":"板歯目"},{"artId":58,"name":"DNA GAINZ"},{"artId":59,"name":"the engy"},{"artId":60,"name":"EOW"},{"artId":61,"name":"ザ・シスターズハイ"},{"artId":62,"name":"ORCALAND"},{"artId":63,"name":"インナージャーニー"},{"artId":64,"name":"カリカヌル女子子"},{"artId":65,"name":"Sundae May Club"},{"artId":66,"name":"u named (radica)"},{"artId":67,"name":"灯橙あか"},{"artId":68,"name":"しまも"},{"artId":69,"name":"ルイ"},{"artId":70,"name":"Leina"},{"artId":71,"name":"Name the Night (2P Style)"},{"artId":72,"name":"小林柊矢"},{"artId":73,"name":"大橋ちっぽけ"},{"artId":74,"name":"aug.1020"},{"artId":75,"name":"『ユイカ』"},{"artId":76,"name":"坂口有望"},{"artId":77,"name":"森大翔"},{"artId":78,"name":"崎山蒼志"},{"artId":79,"name":"渡會将士"},{"artId":80,"name":"ミヤギ・コースタル・セッション 〜MEGA ROCKS 編〜中田裕二＆中村マサトシ"}],"stageList":[{"stageId":0,"stageName":"Rensa","stageNameShort":"Rensa","colorName":"stage-grey"},{"stageId":1,"stageName":"darwin","stageNameShort":"darwin","colorName":"stage-deep-purple"},{"stageId":2,"stageName":"MACANA","stageNameShort":"MACANA","colorName":"stage-grey"},{"stageId":3,"stageName":"ROCKATERIA","stageNameShort":"ROCKATERIA","colorName":"stage-purple"},{"stageId":4,"stageName":"enn 2nd","stageNameShort":"enn 2nd","colorName":"stage-red"},{"stageId":5,"stageName":"enn 3rd","stageNameShort":"enn 3rd","colorName":"stage-blue"},{"stageId":6,"stageName":"Spase Zero","stageNameShort":"Spase Zero","colorName":"stage-yellow"},{"stageId":7,"stageName":"Neo Brotherz","stageNameShort":"Neo Brotherz","colorName":"stage-brown"},{"stageId":8,"stageName":"誰も知らない劇場","stageNameShort":"誰も知らない劇場","colorName":"stage-black"}],"turnList":[{"turnId":0,"startTime":"12:00","min":30,"artId":0,"stageId":0},{"turnId":1,"startTime":"13:00","min":30,"artId":1,"stageId":0},{"turnId":2,"startTime":"14:00","min":30,"artId":2,"stageId":0},{"turnId":3,"startTime":"15:00","min":30,"artId":3,"stageId":0},{"turnId":4,"startTime":"16:00","min":30,"artId":4,"stageId":0},{"turnId":5,"startTime":"17:00","min":30,"artId":5,"stageId":0},{"turnId":6,"startTime":"18:00","min":30,"artId":6,"stageId":0},{"turnId":7,"startTime":"19:00","min":30,"artId":7,"stageId":0},{"turnId":8,"startTime":"20:00","min":30,"artId":8,"stageId":0},{"turnId":9,"startTime":"21:00","min":30,"artId":9,"stageId":0},{"turnId":10,"startTime":"12:30","min":30,"artId":10,"stageId":1},{"turnId":11,"startTime":"13:30","min":30,"artId":11,"stageId":1},{"turnId":12,"startTime":"14:30","min":30,"artId":12,"stageId":1},{"turnId":13,"startTime":"15:30","min":30,"artId":13,"stageId":1},{"turnId":14,"startTime":"16:30","min":30,"artId":14,"stageId":1},{"turnId":15,"startTime":"17:30","min":30,"artId":15,"stageId":1},{"turnId":16,"startTime":"18:30","min":30,"artId":16,"stageId":1},{"turnId":17,"startTime":"19:30","min":30,"artId":17,"stageId":1},{"turnId":18,"startTime":"20:30","min":30,"artId":18,"stageId":1},{"turnId":19,"startTime":"12:00","min":30,"artId":19,"stageId":2},{"turnId":20,"startTime":"13:00","min":30,"artId":20,"stageId":2},{"turnId":21,"startTime":"14:00","min":30,"artId":21,"stageId":2},{"turnId":22,"startTime":"15:00","min":30,"artId":22,"stageId":2},{"turnId":23,"startTime":"16:00","min":30,"artId":23,"stageId":2},{"turnId":24,"startTime":"17:00","min":30,"artId":24,"stageId":2},{"turnId":25,"startTime":"18:00","min":30,"artId":25,"stageId":2},{"turnId":26,"startTime":"19:00","min":30,"artId":26,"stageId":2},{"turnId":27,"startTime":"20:00","min":30,"artId":27,"stageId":2},{"turnId":28,"startTime":"21:00","min":30,"artId":28,"stageId":2},{"turnId":29,"startTime":"12:30","min":30,"artId":29,"stageId":3},{"turnId":30,"startTime":"13:30","min":30,"artId":30,"stageId":3},{"turnId":31,"startTime":"14:30","min":30,"artId":31,"stageId":3},{"turnId":32,"startTime":"15:30","min":30,"artId":32,"stageId":3},{"turnId":33,"startTime":"16:30","min":30,"artId":33,"stageId":3},{"turnId":34,"startTime":"17:30","min":30,"artId":34,"stageId":3},{"turnId":35,"startTime":"18:30","min":30,"artId":35,"stageId":3},{"turnId":36,"startTime":"19:30","min":30,"artId":36,"stageId":3},{"turnId":37,"startTime":"20:30","min":30,"artId":37,"stageId":3},{"turnId":38,"startTime":"12:00","min":30,"artId":38,"stageId":4},{"turnId":39,"startTime":"13:00","min":30,"artId":39,"stageId":4},{"turnId":40,"startTime":"14:00","min":30,"artId":40,"stageId":4},{"turnId":41,"startTime":"15:00","min":30,"artId":41,"stageId":4},{"turnId":42,"startTime":"16:00","min":30,"artId":42,"stageId":4},{"turnId":43,"startTime":"17:00","min":30,"artId":43,"stageId":4},{"turnId":44,"startTime":"18:00","min":30,"artId":44,"stageId":4},{"turnId":45,"startTime":"19:00","min":30,"artId":45,"stageId":4},{"turnId":46,"startTime":"20:00","min":30,"artId":46,"stageId":4},{"turnId":47,"startTime":"21:00","min":30,"artId":47,"stageId":4},{"turnId":48,"startTime":"12:30","min":30,"artId":48,"stageId":5},{"turnId":49,"startTime":"13:30","min":30,"artId":49,"stageId":5},{"turnId":50,"startTime":"14:30","min":30,"artId":50,"stageId":5},{"turnId":51,"startTime":"15:30","min":30,"artId":51,"stageId":5},{"turnId":52,"startTime":"16:30","min":30,"artId":52,"stageId":5},{"turnId":53,"startTime":"17:30","min":30,"artId":53,"stageId":5},{"turnId":54,"startTime":"18:30","min":30,"artId":54,"stageId":5},{"turnId":55,"startTime":"19:30","min":30,"artId":55,"stageId":5},{"turnId":56,"startTime":"20:30","min":30,"artId":56,"stageId":5},{"turnId":57,"startTime":"12:00","min":30,"artId":57,"stageId":6},{"turnId":58,"startTime":"13:00","min":30,"artId":58,"stageId":6},{"turnId":59,"startTime":"14:00","min":30,"artId":59,"stageId":6},{"turnId":60,"startTime":"15:00","min":30,"artId":60,"stageId":6},{"turnId":61,"startTime":"16:00","min":30,"artId":61,"stageId":6},{"turnId":62,"startTime":"17:00","min":30,"artId":62,"stageId":6},{"turnId":63,"startTime":"18:00","min":30,"artId":63,"stageId":6},{"turnId":64,"startTime":"19:00","min":30,"artId":64,"stageId":6},{"turnId":65,"startTime":"20:00","min":30,"artId":65,"stageId":6},{"turnId":66,"startTime":"21:00","min":30,"artId":66,"stageId":6},{"turnId":67,"startTime":"13:30","min":30,"artId":67,"stageId":7},{"turnId":68,"startTime":"14:30","min":30,"artId":68,"stageId":7},{"turnId":69,"startTime":"15:30","min":30,"artId":69,"stageId":7},{"turnId":70,"startTime":"16:30","min":30,"artId":70,"stageId":7},{"turnId":71,"startTime":"17:30","min":30,"artId":71,"stageId":7},{"turnId":72,"startTime":"18:30","min":30,"artId":72,"stageId":7},{"turnId":73,"startTime":"19:30","min":30,"artId":73,"stageId":7},{"turnId":74,"startTime":"13:00","min":30,"artId":74,"stageId":8},{"turnId":75,"startTime":"14:00","min":30,"artId":75,"stageId":8},{"turnId":76,"startTime":"15:00","min":30,"artId":76,"stageId":8},{"turnId":77,"startTime":"16:00","min":30,"artId":77,"stageId":8},{"turnId":78,"startTime":"17:00","min":30,"artId":78,"stageId":8},{"turnId":79,"startTime":"18:00","min":30,"artId":79,"stageId":8},{"turnId":80,"startTime":"19:00","min":60,"artId":80,"stageId":8}]}