{"liveId":395,"jsonVersion":17,"openTime":"9","closeTime":"23","notificationVersion":"9","notification":"ヒロインズの特典会に対応しました｡","artList":[{"artId":0,"name":"AQA"},{"artId":1,"name":"AdamLilith"},{"artId":2,"name":"As a Cutie Pomeranian"},{"artId":3,"name":"CAL&RES"},{"artId":4,"name":"Cent Heaven"},{"artId":5,"name":"ESTLINK☆"},{"artId":6,"name":"EYE CANDY"},{"artId":7,"name":"FES☆TIVE"},{"artId":8,"name":"HAPPY CREATORS"},{"artId":9,"name":"HIGH SPIRITS"},{"artId":10,"name":"I MY ME MINE"},{"artId":11,"name":"Ill"},{"artId":12,"name":"JAPANARIZM"},{"artId":13,"name":"JamsCollection"},{"artId":14,"name":"KOIHAJI"},{"artId":15,"name":"KRD8"},{"artId":16,"name":"LADYBABY"},{"artId":17,"name":"Lily wonder"},{"artId":18,"name":"Lollipop♡CHU"},{"artId":19,"name":"Luce Twinkle Wink☆"},{"artId":20,"name":"Melty BeaR"},{"artId":21,"name":"Milky✳︎Sphene"},{"artId":22,"name":"MyDearDarlin'"},{"artId":23,"name":"NEO BREAK"},{"artId":24,"name":"OS☆U"},{"artId":25,"name":"O₂"},{"artId":26,"name":"Palette Parade"},{"artId":27,"name":"Peel the Apple"},{"artId":28,"name":"Qu♡Aly"},{"artId":29,"name":"Re:Clash"},{"artId":30,"name":"RiNCENT♯"},{"artId":31,"name":"SUPER☆GiRLS"},{"artId":32,"name":"Sweet Alley"},{"artId":33,"name":"TENRIN"},{"artId":34,"name":"THE ENCORE"},{"artId":35,"name":"WT☆Egret"},{"artId":36,"name":"ZUTTOMOTTO"},{"artId":37,"name":"dela"},{"artId":38,"name":"parfait d'ange"},{"artId":39,"name":"あおぞらをキミに"},{"artId":40,"name":"きゅ～くる"},{"artId":41,"name":"すーぱーぷーばぁー!!"},{"artId":42,"name":"なないろ∞ミルキーウェイ"},{"artId":43,"name":"にっぽんワチャチャ"},{"artId":44,"name":"はいどーも！テラスマです！"},{"artId":45,"name":"ぷりしえーる"},{"artId":46,"name":"ぺりきゅらむ"},{"artId":47,"name":"みらくらんど"},{"artId":48,"name":"わーすた"},{"artId":49,"name":"アイドルカレッジ"},{"artId":50,"name":"アップアップガールズ（２）"},{"artId":51,"name":"エラバレシ"},{"artId":52,"name":"カラフルスクリーム"},{"artId":53,"name":"サクヤコノハナ"},{"artId":54,"name":"シークレットシャノワール"},{"artId":55,"name":"ジエメイ"},{"artId":56,"name":"スポポポポニー"},{"artId":57,"name":"ドレスコード"},{"artId":58,"name":"ハレとハレ！"},{"artId":59,"name":"パラディーク"},{"artId":60,"name":"パラレルサイダー"},{"artId":61,"name":"ビーバイユー"},{"artId":62,"name":"ポラライト"},{"artId":63,"name":"ワンダーウィード天"},{"artId":64,"name":"世界逆転宣言！"},{"artId":65,"name":"九州女子翼"},{"artId":66,"name":"可憐なアイボリー"},{"artId":67,"name":"君に、胸キュン。"},{"artId":68,"name":"夏空のオリオン"},{"artId":69,"name":"夜宙☆ShiNew'"},{"artId":70,"name":"天空のシラバス"},{"artId":71,"name":"手羽先センセーション"},{"artId":72,"name":"月に足跡を残した少女達は一体何を見たのか..."},{"artId":73,"name":"点染テンセイ少女。"},{"artId":74,"name":"煌めき☆アンフォレント"},{"artId":75,"name":"脳内パステル"},{"artId":76,"name":"花いろは"},{"artId":77,"name":"虹色の飛行少女"},{"artId":78,"name":"蜜兎"}],"stageList":[{"stageId":0,"stageName":"徳川","stageNameShort":"徳川","colorName":"stage-red","stageOrder":0},{"stageId":1,"stageName":"豊臣","stageNameShort":"豊臣","colorName":"stage-blue","stageOrder":1},{"stageId":2,"stageName":"戦国","stageNameShort":"戦国","colorName":"stage-green","stageOrder":2},{"stageId":3,"stageName":"桃配","stageNameShort":"桃配","colorName":"stage-pink","stageOrder":3},{"stageId":4,"stageName":"下剋上","stageNameShort":"下剋上","colorName":"stage-yellow","stageOrder":4},{"stageId":5,"stageName":"物販4","stageNameShort":"物販4","colorName":"stage-grey","stageOrder":8},{"stageId":6,"stageName":"物販5","stageNameShort":"物販5","colorName":"stage-grey","stageOrder":9},{"stageId":7,"stageName":"物販6","stageNameShort":"物販6","colorName":"stage-grey","stageOrder":10},{"stageId":8,"stageName":"物販7","stageNameShort":"物販7","colorName":"stage-grey","stageOrder":11},{"stageId":9,"stageName":"物販8","stageNameShort":"物販8","colorName":"stage-grey","stageOrder":12},{"stageId":10,"stageName":"物販9","stageNameShort":"物販9","colorName":"stage-grey","stageOrder":13},{"stageId":11,"stageName":"物販10","stageNameShort":"物販10","colorName":"stage-grey","stageOrder":14},{"stageId":12,"stageName":"物販11","stageNameShort":"物販11","colorName":"stage-grey","stageOrder":15},{"stageId":13,"stageName":"物販12","stageNameShort":"物販12","colorName":"stage-grey","stageOrder":16},{"stageId":14,"stageName":"物販13","stageNameShort":"物販13","colorName":"stage-grey","stageOrder":17},{"stageId":15,"stageName":"物販14","stageNameShort":"物販14","colorName":"stage-grey","stageOrder":18},{"stageId":16,"stageName":"物販15","stageNameShort":"物販15","colorName":"stage-grey","stageOrder":19},{"stageId":17,"stageName":"物販16","stageNameShort":"物販16","colorName":"stage-grey","stageOrder":20},{"stageId":18,"stageName":"物販17","stageNameShort":"物販17","colorName":"stage-grey","stageOrder":21},{"stageId":19,"stageName":"物販18","stageNameShort":"物販18","colorName":"stage-grey","stageOrder":22},{"stageId":20,"stageName":"物販19","stageNameShort":"物販19","colorName":"stage-grey","stageOrder":23},{"stageId":21,"stageName":"物販20","stageNameShort":"物販20","colorName":"stage-grey","stageOrder":24},{"stageId":22,"stageName":"物販21","stageNameShort":"物販21","colorName":"stage-grey","stageOrder":25},{"stageId":23,"stageName":"物販22","stageNameShort":"物販22","colorName":"stage-grey","stageOrder":26},{"stageId":24,"stageName":"物販23","stageNameShort":"物販23","colorName":"stage-grey","stageOrder":27},{"stageId":25,"stageName":"物販24","stageNameShort":"物販24","colorName":"stage-grey","stageOrder":28},{"stageId":26,"stageName":"物販25","stageNameShort":"物販25","colorName":"stage-grey","stageOrder":29},{"stageId":27,"stageName":"物販26","stageNameShort":"物販26","colorName":"stage-grey","stageOrder":30},{"stageId":28,"stageName":"物販27","stageNameShort":"物販27","colorName":"stage-grey","stageOrder":31},{"stageId":29,"stageName":"物販28","stageNameShort":"物販28","colorName":"stage-grey","stageOrder":32},{"stageId":30,"stageName":"物販29","stageNameShort":"物販29","colorName":"stage-grey","stageOrder":33},{"stageId":31,"stageName":"物販1","stageNameShort":"物販1","colorName":"stage-grey","stageOrder":5},{"stageId":32,"stageName":"物販2","stageNameShort":"物販2","colorName":"stage-grey","stageOrder":6},{"stageId":33,"stageName":"物販3","stageNameShort":"物販3","colorName":"stage-grey","stageOrder":7}],"turnList":[{"turnId":0,"startTime":"09:30","min":25,"artId":77,"stageId":0},{"turnId":1,"startTime":"09:55","min":20,"artId":37,"stageId":0},{"turnId":2,"startTime":"10:15","min":20,"artId":49,"stageId":0},{"turnId":3,"startTime":"10:35","min":20,"artId":28,"stageId":0},{"turnId":4,"startTime":"11:00","min":20,"artId":1,"stageId":0},{"turnId":5,"startTime":"11:20","min":20,"artId":11,"stageId":0},{"turnId":6,"startTime":"11:40","min":20,"artId":9,"stageId":0},{"turnId":7,"startTime":"12:05","min":20,"artId":31,"stageId":0},{"turnId":8,"startTime":"12:25","min":20,"artId":65,"stageId":0},{"turnId":9,"startTime":"12:45","min":20,"artId":33,"stageId":0},{"turnId":10,"startTime":"13:10","min":20,"artId":27,"stageId":0},{"turnId":11,"startTime":"13:30","min":20,"artId":50,"stageId":0},{"turnId":12,"startTime":"13:50","min":25,"artId":13,"stageId":0},{"turnId":13,"startTime":"14:20","min":20,"artId":32,"stageId":0},{"turnId":14,"startTime":"14:40","min":20,"artId":57,"stageId":0},{"turnId":15,"startTime":"15:00","min":20,"artId":26,"stageId":0},{"turnId":16,"startTime":"15:20","min":20,"artId":66,"stageId":0},{"turnId":17,"startTime":"15:45","min":20,"artId":71,"stageId":0},{"turnId":18,"startTime":"16:05","min":20,"artId":76,"stageId":0},{"turnId":19,"startTime":"16:25","min":20,"artId":74,"stageId":0},{"turnId":20,"startTime":"16:45","min":20,"artId":55,"stageId":0},{"turnId":21,"startTime":"17:10","min":25,"artId":48,"stageId":0},{"turnId":22,"startTime":"17:35","min":20,"artId":34,"stageId":0},{"turnId":23,"startTime":"17:55","min":20,"artId":63,"stageId":0},{"turnId":24,"startTime":"18:20","min":20,"artId":52,"stageId":0},{"turnId":25,"startTime":"18:40","min":20,"artId":22,"stageId":0},{"turnId":26,"startTime":"19:00","min":25,"artId":67,"stageId":0},{"turnId":27,"startTime":"19:25","min":25,"artId":7,"stageId":0},{"turnId":28,"startTime":"09:40","min":20,"artId":62,"stageId":1},{"turnId":29,"startTime":"10:00","min":20,"artId":19,"stageId":1},{"turnId":30,"startTime":"10:20","min":20,"artId":3,"stageId":1},{"turnId":31,"startTime":"10:45","min":20,"artId":64,"stageId":1},{"turnId":32,"startTime":"11:05","min":20,"artId":21,"stageId":1},{"turnId":33,"startTime":"11:25","min":20,"artId":10,"stageId":1},{"turnId":34,"startTime":"11:50","min":20,"artId":25,"stageId":1},{"turnId":35,"startTime":"12:10","min":20,"artId":54,"stageId":1},{"turnId":36,"startTime":"12:30","min":20,"artId":72,"stageId":1},{"turnId":37,"startTime":"12:50","min":20,"artId":74,"stageId":1},{"turnId":38,"startTime":"13:15","min":20,"artId":22,"stageId":1},{"turnId":39,"startTime":"13:35","min":20,"artId":2,"stageId":1},{"turnId":40,"startTime":"13:55","min":20,"artId":23,"stageId":1},{"turnId":41,"startTime":"14:20","min":20,"artId":53,"stageId":1},{"turnId":42,"startTime":"14:40","min":20,"artId":49,"stageId":1},{"turnId":43,"startTime":"15:00","min":20,"artId":30,"stageId":1},{"turnId":44,"startTime":"15:25","min":20,"artId":67,"stageId":1},{"turnId":45,"startTime":"15:45","min":20,"artId":52,"stageId":1},{"turnId":46,"startTime":"16:05","min":20,"artId":59,"stageId":1},{"turnId":47,"startTime":"16:25","min":20,"artId":31,"stageId":1},{"turnId":48,"startTime":"16:50","min":20,"artId":8,"stageId":1},{"turnId":49,"startTime":"17:10","min":20,"artId":51,"stageId":1},{"turnId":50,"startTime":"17:30","min":20,"artId":13,"stageId":1},{"turnId":51,"startTime":"17:50","min":20,"artId":12,"stageId":1},{"turnId":52,"startTime":"18:15","min":20,"artId":68,"stageId":1},{"turnId":53,"startTime":"18:35","min":20,"artId":24,"stageId":1},{"turnId":54,"startTime":"18:55","min":20,"artId":73,"stageId":1},{"turnId":55,"startTime":"19:15","min":20,"artId":32,"stageId":1},{"turnId":56,"startTime":"09:35","min":20,"artId":78,"stageId":2},{"turnId":57,"startTime":"09:55","min":15,"artId":18,"stageId":2},{"turnId":58,"startTime":"10:10","min":15,"artId":44,"stageId":2},{"turnId":59,"startTime":"10:25","min":20,"artId":26,"stageId":2},{"turnId":60,"startTime":"10:55","min":15,"artId":46,"stageId":2},{"turnId":61,"startTime":"11:10","min":15,"artId":29,"stageId":2},{"turnId":62,"startTime":"11:25","min":15,"artId":20,"stageId":2},{"turnId":63,"startTime":"11:45","min":20,"artId":66,"stageId":2},{"turnId":64,"startTime":"12:05","min":15,"artId":60,"stageId":2},{"turnId":65,"startTime":"12:20","min":15,"artId":16,"stageId":2},{"turnId":66,"startTime":"12:35","min":20,"artId":63,"stageId":2},{"turnId":67,"startTime":"12:55","min":15,"artId":73,"stageId":2},{"turnId":68,"startTime":"13:15","min":15,"artId":43,"stageId":2},{"turnId":69,"startTime":"13:30","min":15,"artId":56,"stageId":2},{"turnId":70,"startTime":"13:45","min":15,"artId":38,"stageId":2},{"turnId":71,"startTime":"14:00","min":15,"artId":36,"stageId":2},{"turnId":72,"startTime":"14:15","min":20,"artId":7,"stageId":2},{"turnId":73,"startTime":"14:40","min":15,"artId":24,"stageId":2},{"turnId":74,"startTime":"14:55","min":15,"artId":75,"stageId":2},{"turnId":75,"startTime":"15:10","min":15,"artId":11,"stageId":2},{"turnId":76,"startTime":"15:25","min":15,"artId":40,"stageId":2},{"turnId":77,"startTime":"15:40","min":15,"artId":17,"stageId":2},{"turnId":78,"startTime":"16:00","min":15,"artId":9,"stageId":2},{"turnId":79,"startTime":"16:15","min":15,"artId":5,"stageId":2},{"turnId":80,"startTime":"16:30","min":15,"artId":33,"stageId":2},{"turnId":81,"startTime":"16:45","min":15,"artId":35,"stageId":2},{"turnId":82,"startTime":"17:10","min":15,"artId":50,"stageId":2},{"turnId":83,"startTime":"17:25","min":15,"artId":0,"stageId":2},{"turnId":84,"startTime":"17:40","min":15,"artId":41,"stageId":2},{"turnId":85,"startTime":"17:55","min":15,"artId":69,"stageId":2},{"turnId":86,"startTime":"18:20","min":15,"artId":53,"stageId":2},{"turnId":87,"startTime":"18:35","min":15,"artId":39,"stageId":2},{"turnId":88,"startTime":"18:50","min":20,"artId":15,"stageId":2},{"turnId":89,"startTime":"19:10","min":20,"artId":71,"stageId":2},{"turnId":90,"startTime":"09:35","min":20,"artId":43,"stageId":3},{"turnId":91,"startTime":"09:55","min":15,"artId":36,"stageId":3},{"turnId":92,"startTime":"10:10","min":15,"artId":6,"stageId":3},{"turnId":93,"startTime":"10:25","min":15,"artId":42,"stageId":3},{"turnId":94,"startTime":"10:40","min":15,"artId":56,"stageId":3},{"turnId":95,"startTime":"11:00","min":15,"artId":51,"stageId":3},{"turnId":96,"startTime":"11:15","min":15,"artId":40,"stageId":3},{"turnId":97,"startTime":"11:30","min":15,"artId":76,"stageId":3},{"turnId":98,"startTime":"11:45","min":15,"artId":57,"stageId":3},{"turnId":99,"startTime":"12:00","min":15,"artId":35,"stageId":3},{"turnId":100,"startTime":"12:20","min":15,"artId":8,"stageId":3},{"turnId":101,"startTime":"12:35","min":15,"artId":41,"stageId":3},{"turnId":102,"startTime":"12:50","min":15,"artId":37,"stageId":3},{"turnId":103,"startTime":"13:05","min":15,"artId":19,"stageId":3},{"turnId":104,"startTime":"13:20","min":15,"artId":59,"stageId":3},{"turnId":105,"startTime":"13:40","min":15,"artId":3,"stageId":3},{"turnId":106,"startTime":"13:55","min":15,"artId":34,"stageId":3},{"turnId":107,"startTime":"14:10","min":15,"artId":14,"stageId":3},{"turnId":108,"startTime":"14:25","min":15,"artId":1,"stageId":3},{"turnId":109,"startTime":"14:45","min":15,"artId":4,"stageId":3},{"turnId":110,"startTime":"15:00","min":15,"artId":54,"stageId":3},{"turnId":111,"startTime":"15:15","min":15,"artId":62,"stageId":3},{"turnId":112,"startTime":"15:30","min":15,"artId":60,"stageId":3},{"turnId":113,"startTime":"15:45","min":15,"artId":15,"stageId":3},{"turnId":114,"startTime":"16:05","min":15,"artId":46,"stageId":3},{"turnId":115,"startTime":"16:20","min":15,"artId":20,"stageId":3},{"turnId":116,"startTime":"16:35","min":15,"artId":72,"stageId":3},{"turnId":117,"startTime":"16:50","min":15,"artId":16,"stageId":3},{"turnId":118,"startTime":"17:10","min":15,"artId":78,"stageId":3},{"turnId":119,"startTime":"17:25","min":15,"artId":58,"stageId":3},{"turnId":120,"startTime":"17:40","min":15,"artId":70,"stageId":3},{"turnId":121,"startTime":"17:55","min":15,"artId":65,"stageId":3},{"turnId":122,"startTime":"18:10","min":15,"artId":2,"stageId":3},{"turnId":123,"startTime":"18:30","min":15,"artId":25,"stageId":3},{"turnId":124,"startTime":"18:45","min":15,"artId":45,"stageId":3},{"turnId":125,"startTime":"19:00","min":15,"artId":47,"stageId":3},{"turnId":126,"startTime":"19:15","min":20,"artId":75,"stageId":3},{"turnId":127,"startTime":"10:15","min":20,"artId":4,"stageId":4},{"turnId":128,"startTime":"10:35","min":20,"artId":38,"stageId":4},{"turnId":129,"startTime":"10:55","min":20,"artId":14,"stageId":4},{"turnId":130,"startTime":"11:15","min":20,"artId":58,"stageId":4},{"turnId":131,"startTime":"11:45","min":20,"artId":17,"stageId":4},{"turnId":132,"startTime":"12:05","min":20,"artId":70,"stageId":4},{"turnId":133,"startTime":"12:25","min":20,"artId":69,"stageId":4},{"turnId":134,"startTime":"12:55","min":20,"artId":5,"stageId":4},{"turnId":135,"startTime":"13:15","min":20,"artId":0,"stageId":4},{"turnId":136,"startTime":"13:35","min":20,"artId":61,"stageId":4},{"turnId":137,"startTime":"14:10","min":20,"artId":12,"stageId":4},{"turnId":138,"startTime":"14:30","min":20,"artId":18,"stageId":4},{"turnId":139,"startTime":"14:50","min":20,"artId":45,"stageId":4},{"turnId":140,"startTime":"15:10","min":20,"artId":39,"stageId":4},{"turnId":141,"startTime":"15:40","min":20,"artId":47,"stageId":4},{"turnId":142,"startTime":"16:00","min":20,"artId":44,"stageId":4},{"turnId":143,"startTime":"16:20","min":20,"artId":28,"stageId":4},{"turnId":144,"startTime":"16:50","min":20,"artId":64,"stageId":4},{"turnId":145,"startTime":"17:10","min":20,"artId":42,"stageId":4},{"turnId":146,"startTime":"17:30","min":20,"artId":29,"stageId":4},{"turnId":147,"startTime":"10:20","min":80,"artId":77,"stageId":5},{"turnId":148,"startTime":"12:25","min":80,"artId":9,"stageId":5},{"turnId":149,"startTime":"15:00","min":80,"artId":32,"stageId":5},{"turnId":150,"startTime":"17:05","min":80,"artId":74,"stageId":5},{"turnId":151,"startTime":"19:00","min":80,"artId":52,"stageId":5},{"turnId":152,"startTime":"10:40","min":80,"artId":37,"stageId":6},{"turnId":153,"startTime":"12:50","min":80,"artId":31,"stageId":6},{"turnId":154,"startTime":"15:40","min":80,"artId":26,"stageId":6},{"turnId":155,"startTime":"17:25","min":80,"artId":55,"stageId":6},{"turnId":156,"startTime":"11:00","min":80,"artId":49,"stageId":7},{"turnId":157,"startTime":"13:55","min":80,"artId":27,"stageId":7},{"turnId":158,"startTime":"16:05","min":80,"artId":66,"stageId":7},{"turnId":159,"startTime":"17:55","min":80,"artId":48,"stageId":7},{"turnId":160,"startTime":"19:45","min":80,"artId":67,"stageId":7},{"turnId":161,"startTime":"11:20","min":80,"artId":28,"stageId":8},{"turnId":162,"startTime":"14:15","min":80,"artId":50,"stageId":8},{"turnId":163,"startTime":"16:30","min":80,"artId":71,"stageId":8},{"turnId":164,"startTime":"18:15","min":80,"artId":34,"stageId":8},{"turnId":165,"startTime":"20:00","min":80,"artId":7,"stageId":8},{"turnId":166,"startTime":"13:00","min":80,"artId":65,"stageId":9},{"turnId":167,"startTime":"14:40","min":80,"artId":13,"stageId":9},{"turnId":168,"startTime":"16:50","min":80,"artId":76,"stageId":9},{"turnId":169,"startTime":"18:35","min":80,"artId":63,"stageId":9},{"turnId":170,"startTime":"10:20","min":80,"artId":62,"stageId":10},{"turnId":171,"startTime":"12:35","min":80,"artId":25,"stageId":10},{"turnId":172,"startTime":"14:20","min":80,"artId":2,"stageId":10},{"turnId":173,"startTime":"16:05","min":80,"artId":67,"stageId":10},{"turnId":174,"startTime":"18:30","min":80,"artId":12,"stageId":10},{"turnId":175,"startTime":"10:45","min":80,"artId":19,"stageId":11},{"turnId":176,"startTime":"12:55","min":80,"artId":54,"stageId":11},{"turnId":177,"startTime":"14:35","min":80,"artId":23,"stageId":11},{"turnId":178,"startTime":"16:25","min":80,"artId":52,"stageId":11},{"turnId":179,"startTime":"18:55","min":80,"artId":68,"stageId":11},{"turnId":180,"startTime":"11:30","min":80,"artId":64,"stageId":12},{"turnId":181,"startTime":"13:15","min":80,"artId":72,"stageId":12},{"turnId":182,"startTime":"15:05","min":80,"artId":53,"stageId":12},{"turnId":183,"startTime":"19:15","min":80,"artId":24,"stageId":12},{"turnId":184,"startTime":"11:50","min":80,"artId":21,"stageId":13},{"turnId":185,"startTime":"13:30","min":80,"artId":74,"stageId":13},{"turnId":186,"startTime":"15:25","min":80,"artId":49,"stageId":13},{"turnId":187,"startTime":"17:50","min":80,"artId":51,"stageId":13},{"turnId":188,"startTime":"19:40","min":80,"artId":73,"stageId":13},{"turnId":189,"startTime":"12:05","min":80,"artId":10,"stageId":14},{"turnId":190,"startTime":"14:00","min":90,"artId":22,"stageId":14},{"turnId":191,"startTime":"15:40","min":80,"artId":30,"stageId":14},{"turnId":192,"startTime":"18:15","min":80,"artId":13,"stageId":14},{"turnId":193,"startTime":"19:55","min":80,"artId":32,"stageId":14},{"turnId":194,"startTime":"10:15","min":80,"artId":78,"stageId":15},{"turnId":195,"startTime":"12:00","min":80,"artId":20,"stageId":15},{"turnId":196,"startTime":"14:25","min":80,"artId":38,"stageId":15},{"turnId":197,"startTime":"16:35","min":80,"artId":9,"stageId":15},{"turnId":198,"startTime":"18:20","min":80,"artId":41,"stageId":15},{"turnId":199,"startTime":"10:30","min":80,"artId":18,"stageId":16},{"turnId":200,"startTime":"12:25","min":80,"artId":66,"stageId":16},{"turnId":201,"startTime":"14:55","min":80,"artId":7,"stageId":16},{"turnId":202,"startTime":"19:00","min":80,"artId":53,"stageId":16},{"turnId":203,"startTime":"10:55","min":80,"artId":44,"stageId":17},{"turnId":204,"startTime":"13:20","min":80,"artId":63,"stageId":17},{"turnId":205,"startTime":"15:20","min":80,"artId":24,"stageId":17},{"turnId":206,"startTime":"17:05","min":80,"artId":5,"stageId":17},{"turnId":207,"startTime":"19:15","min":80,"artId":39,"stageId":17},{"turnId":208,"startTime":"11:10","min":80,"artId":26,"stageId":18},{"turnId":209,"startTime":"13:35","min":80,"artId":73,"stageId":18},{"turnId":210,"startTime":"15:35","min":80,"artId":75,"stageId":18},{"turnId":211,"startTime":"17:25","min":80,"artId":35,"stageId":18},{"turnId":212,"startTime":"19:35","min":80,"artId":15,"stageId":18},{"turnId":213,"startTime":"11:35","min":80,"artId":46,"stageId":19},{"turnId":214,"startTime":"13:55","min":80,"artId":43,"stageId":19},{"turnId":215,"startTime":"16:00","min":80,"artId":40,"stageId":19},{"turnId":216,"startTime":"17:50","min":80,"artId":50,"stageId":19},{"turnId":217,"startTime":"19:50","min":80,"artId":71,"stageId":19},{"turnId":218,"startTime":"11:50","min":80,"artId":29,"stageId":20},{"turnId":219,"startTime":"14:10","min":80,"artId":56,"stageId":20},{"turnId":220,"startTime":"16:15","min":80,"artId":17,"stageId":20},{"turnId":221,"startTime":"18:05","min":80,"artId":0,"stageId":20},{"turnId":222,"startTime":"10:20","min":80,"artId":43,"stageId":21},{"turnId":223,"startTime":"12:15","min":80,"artId":76,"stageId":21},{"turnId":224,"startTime":"14:35","min":80,"artId":34,"stageId":21},{"turnId":225,"startTime":"16:45","min":80,"artId":46,"stageId":21},{"turnId":226,"startTime":"18:35","min":80,"artId":69,"stageId":21},{"turnId":227,"startTime":"10:50","min":80,"artId":6,"stageId":22},{"turnId":228,"startTime":"12:35","min":80,"artId":35,"stageId":22},{"turnId":229,"startTime":"14:50","min":80,"artId":14,"stageId":22},{"turnId":230,"startTime":"17:00","min":80,"artId":20,"stageId":22},{"turnId":231,"startTime":"18:35","min":80,"artId":65,"stageId":22},{"turnId":232,"startTime":"11:10","min":80,"artId":42,"stageId":23},{"turnId":233,"startTime":"13:00","min":80,"artId":8,"stageId":23},{"turnId":234,"startTime":"15:25","min":80,"artId":4,"stageId":23},{"turnId":235,"startTime":"17:15","min":80,"artId":72,"stageId":23},{"turnId":236,"startTime":"18:50","min":80,"artId":2,"stageId":23},{"turnId":237,"startTime":"11:25","min":80,"artId":56,"stageId":24},{"turnId":238,"startTime":"13:15","min":80,"artId":41,"stageId":24},{"turnId":239,"startTime":"15:40","min":80,"artId":54,"stageId":24},{"turnId":240,"startTime":"17:45","min":80,"artId":78,"stageId":24},{"turnId":241,"startTime":"11:40","min":80,"artId":51,"stageId":25},{"turnId":242,"startTime":"13:30","min":80,"artId":37,"stageId":25},{"turnId":243,"startTime":"15:55","min":80,"artId":62,"stageId":25},{"turnId":244,"startTime":"18:05","min":80,"artId":58,"stageId":25},{"turnId":245,"startTime":"11:55","min":80,"artId":40,"stageId":26},{"turnId":246,"startTime":"13:45","min":80,"artId":19,"stageId":26},{"turnId":247,"startTime":"16:30","min":80,"artId":15,"stageId":26},{"turnId":248,"startTime":"18:20","min":80,"artId":70,"stageId":26},{"turnId":249,"startTime":"11:00","min":80,"artId":4,"stageId":27},{"turnId":250,"startTime":"12:35","min":80,"artId":17,"stageId":27},{"turnId":251,"startTime":"14:10","min":80,"artId":0,"stageId":27},{"turnId":252,"startTime":"15:40","min":80,"artId":45,"stageId":27},{"turnId":253,"startTime":"17:10","min":80,"artId":28,"stageId":27},{"turnId":254,"startTime":"19:05","min":80,"artId":25,"stageId":27},{"turnId":255,"startTime":"11:20","min":80,"artId":38,"stageId":28},{"turnId":256,"startTime":"12:50","min":80,"artId":70,"stageId":28},{"turnId":257,"startTime":"14:20","min":80,"artId":61,"stageId":28},{"turnId":258,"startTime":"15:55","min":80,"artId":39,"stageId":28},{"turnId":259,"startTime":"17:30","min":80,"artId":64,"stageId":28},{"turnId":260,"startTime":"19:25","min":80,"artId":45,"stageId":28},{"turnId":261,"startTime":"11:40","min":80,"artId":14,"stageId":29},{"turnId":262,"startTime":"13:10","min":80,"artId":69,"stageId":29},{"turnId":263,"startTime":"14:40","min":80,"artId":12,"stageId":29},{"turnId":264,"startTime":"16:20","min":80,"artId":47,"stageId":29},{"turnId":265,"startTime":"17:55","min":80,"artId":42,"stageId":29},{"turnId":266,"startTime":"19:40","min":80,"artId":47,"stageId":29},{"turnId":267,"startTime":"12:00","min":80,"artId":58,"stageId":30},{"turnId":268,"startTime":"13:40","min":80,"artId":5,"stageId":30},{"turnId":269,"startTime":"15:15","min":80,"artId":18,"stageId":30},{"turnId":270,"startTime":"16:50","min":80,"artId":44,"stageId":30},{"turnId":271,"startTime":"18:20","min":80,"artId":29,"stageId":30},{"turnId":272,"startTime":"19:55","min":80,"artId":75,"stageId":30},{"turnId":273,"startTime":"11:50","min":50,"artId":1,"stageId":31},{"turnId":274,"startTime":"13:10","min":50,"artId":57,"stageId":31},{"turnId":275,"startTime":"14:40","min":50,"artId":36,"stageId":31},{"turnId":276,"startTime":"11:00","min":50,"artId":3,"stageId":32},{"turnId":277,"startTime":"12:10","min":50,"artId":11,"stageId":32},{"turnId":278,"startTime":"13:10","min":50,"artId":16,"stageId":32},{"turnId":279,"startTime":"14:40","min":50,"artId":33,"stageId":32},{"turnId":280,"startTime":"16:00","min":50,"artId":60,"stageId":32},{"turnId":281,"startTime":"14:00","min":50,"artId":59,"stageId":33}]}