[
  {
    "icon": "mdi-alarm-plus",
    "date": "7/14",
    "message": "SPARK IN YAMANAKAKOを更新しました。夏祭り特典会は追加しましたが、各グループの物販は公式から公開されていないため各グループからの情報をご確認ください。"
  },
  {
    "icon": "mdi-alarm-plus",
    "date": "7/12",
    "message": "RISING SUN ROCK FESTIVALタイテに対応しました。"
  },
  {
    "icon": "mdi-alarm-plus",
    "date": "7/12",
    "message": "ROCK IN JAPAN出演者変更に対応しました。"
  },
  {
    "icon": "mdi-alarm-plus",
    "date": "7/12",
    "message": "関ケ原唄姫合戦タイテに対応しました。"
  },
  {
    "icon": "mdi-alarm-plus",
    "date": "7/11",
    "message": "FUJI ROCKタイテに対応しました。"
  },
  {
    "icon": "mdi-alarm-plus",
    "date": "7/11",
    "message": "JOIN ALIVEタイテに対応しました。"
  },
  {
    "icon": "mdi-alarm-plus",
    "date": "7/8",
    "message": "SPARK IN YAMANAKAKOを更新しました。"
  },
  {
    "icon": "mdi-alarm-plus",
    "date": "7/8",
    "message": "IDOL Galaxy7/8代打出演があったので更新しました。物販情報は無いため更新していません。"
  },
  {
    "icon": "mdi-alarm-plus",
    "date": "7/4",
    "message": "IDOL Galaxy7/9タイテ更新に対応しました。自動配信されています。"
  },
  {
    "icon": "mdi-alarm-plus",
    "date": "7/2",
    "message": "SPARK IN YAMANAKAKOに対応しました。自動配信されています。"
  },
  {
    "icon": "mdi-alarm-plus",
    "date": "7/1",
    "message": "ROCK IN JAPANに対応しました。自動配信されています。"
  },
  {
    "icon": "mdi-alarm-plus",
    "date": "7/1",
    "message": "見放題2023のアーティスト変更に対応しました。自動配信されています。"
  },
  {
    "icon": "mdi-cellphone-arrow-down",
    "date": "6/30",
    "message": "同一ライブの別日付をタイムテーブル画面から選択できるように対応しました。"
  },
  {
    "icon": "mdi-cellphone-arrow-down",
    "date": "6/30",
    "message": "各ライブのタイムテーブル情報を一度ダウンロードしたら、オフライン状態でも過去のタイムテーブルを表示できるように対応しました。"
  }
]